<?xml version="1.0" encoding="utf-8"?>
<ArrayOfTuningDetail xmlns:xsi="http://www.w3.org/2001/XMLSchema-instance" xmlns:xsd="http://www.w3.org/2001/XMLSchema">
  <TuningDetail>
    <BroadcastStandard>DvbS2</BroadcastStandard>
    <SatellitePosition>-275</SatellitePosition>
    <Frequency>3648000</Frequency>
    <SymbolRate>30000</SymbolRate>
    <Polarisation>CircularRight</Polarisation>
    <ModulationScheme>Psk4</ModulationScheme>
    <FecCodeRate>Rate3_4</FecCodeRate>
    <PilotTonesState>Off</PilotTonesState>
    <RollOffFactor>ThirtyFive</RollOffFactor>
    <StreamId>0</StreamId>
  </TuningDetail>
  <TuningDetail>
    <BroadcastStandard>DvbS</BroadcastStandard>
    <SatellitePosition>-275</SatellitePosition>
    <Frequency>3718000</Frequency>
    <SymbolRate>12000</SymbolRate>
    <Polarisation>CircularRight</Polarisation>
    <ModulationScheme>Psk4</ModulationScheme>
    <FecCodeRate>Rate1_2</FecCodeRate>
  </TuningDetail>
  <TuningDetail>
    <BroadcastStandard>DvbS2</BroadcastStandard>
    <SatellitePosition>-275</SatellitePosition>
    <Frequency>3723000</Frequency>
    <SymbolRate>21092</SymbolRate>
    <Polarisation>CircularRight</Polarisation>
    <ModulationScheme>Psk4</ModulationScheme>
    <FecCodeRate>Rate3_4</FecCodeRate>
    <PilotTonesState>Off</PilotTonesState>
    <RollOffFactor>ThirtyFive</RollOffFactor>
    <StreamId>0</StreamId>
  </TuningDetail>
  <TuningDetail>
    <BroadcastStandard>DvbS2</BroadcastStandard>
    <SatellitePosition>-275</SatellitePosition>
    <Frequency>3759000</Frequency>
    <SymbolRate>26665</SymbolRate>
    <Polarisation>CircularRight</Polarisation>
    <ModulationScheme>Psk4</ModulationScheme>
    <FecCodeRate>Rate3_4</FecCodeRate>
    <PilotTonesState>Off</PilotTonesState>
    <RollOffFactor>ThirtyFive</RollOffFactor>
    <StreamId>0</StreamId>
  </TuningDetail>
  <TuningDetail>
    <BroadcastStandard>DvbS</BroadcastStandard>
    <SatellitePosition>-275</SatellitePosition>
    <Frequency>3764000</Frequency>
    <SymbolRate>24450</SymbolRate>
    <Polarisation>CircularRight</Polarisation>
    <ModulationScheme>Psk4</ModulationScheme>
    <FecCodeRate>Rate3_4</FecCodeRate>
  </TuningDetail>
  <TuningDetail>
    <BroadcastStandard>DvbS</BroadcastStandard>
    <SatellitePosition>-275</SatellitePosition>
    <Frequency>3784000</Frequency>
    <SymbolRate>6510</SymbolRate>
    <Polarisation>CircularLeft</Polarisation>
    <ModulationScheme>Psk4</ModulationScheme>
    <FecCodeRate>Rate2_3</FecCodeRate>
  </TuningDetail>
  <TuningDetail>
    <BroadcastStandard>DvbS</BroadcastStandard>
    <SatellitePosition>-275</SatellitePosition>
    <Frequency>3791000</Frequency>
    <SymbolRate>6510</SymbolRate>
    <Polarisation>CircularLeft</Polarisation>
    <ModulationScheme>Psk4</ModulationScheme>
    <FecCodeRate>Rate2_3</FecCodeRate>
  </TuningDetail>
  <TuningDetail>
    <BroadcastStandard>DvbS2</BroadcastStandard>
    <SatellitePosition>-275</SatellitePosition>
    <Frequency>3795000</Frequency>
    <SymbolRate>7000</SymbolRate>
    <Polarisation>CircularRight</Polarisation>
    <ModulationScheme>Psk8</ModulationScheme>
    <FecCodeRate>Rate2_3</FecCodeRate>
    <PilotTonesState>On</PilotTonesState>
    <RollOffFactor>ThirtyFive</RollOffFactor>
    <StreamId>0</StreamId>
  </TuningDetail>
  <TuningDetail>
    <BroadcastStandard>DvbS</BroadcastStandard>
    <SatellitePosition>-275</SatellitePosition>
    <Frequency>3800000</Frequency>
    <SymbolRate>2400</SymbolRate>
    <Polarisation>CircularRight</Polarisation>
    <ModulationScheme>Psk4</ModulationScheme>
    <FecCodeRate>Rate3_4</FecCodeRate>
  </TuningDetail>
  <TuningDetail>
    <BroadcastStandard>DvbS</BroadcastStandard>
    <SatellitePosition>-275</SatellitePosition>
    <Frequency>3802000</Frequency>
    <SymbolRate>2000</SymbolRate>
    <Polarisation>CircularRight</Polarisation>
    <ModulationScheme>Psk4</ModulationScheme>
    <FecCodeRate>Rate2_3</FecCodeRate>
  </TuningDetail>
  <TuningDetail>
    <BroadcastStandard>DvbS</BroadcastStandard>
    <SatellitePosition>-275</SatellitePosition>
    <Frequency>3831000</Frequency>
    <SymbolRate>5787</SymbolRate>
    <Polarisation>CircularRight</Polarisation>
    <ModulationScheme>Psk4</ModulationScheme>
    <FecCodeRate>Rate3_4</FecCodeRate>
  </TuningDetail>
  <TuningDetail>
    <BroadcastStandard>DvbS</BroadcastStandard>
    <SatellitePosition>-275</SatellitePosition>
    <Frequency>3838000</Frequency>
    <SymbolRate>7235</SymbolRate>
    <Polarisation>CircularRight</Polarisation>
    <ModulationScheme>Psk4</ModulationScheme>
    <FecCodeRate>Rate3_4</FecCodeRate>
  </TuningDetail>
  <TuningDetail>
    <BroadcastStandard>DvbS2</BroadcastStandard>
    <SatellitePosition>-275</SatellitePosition>
    <Frequency>3855000</Frequency>
    <SymbolRate>4134</SymbolRate>
    <Polarisation>CircularLeft</Polarisation>
    <ModulationScheme>Psk8</ModulationScheme>
    <FecCodeRate>Rate3_4</FecCodeRate>
    <PilotTonesState>On</PilotTonesState>
    <RollOffFactor>ThirtyFive</RollOffFactor>
    <StreamId>0</StreamId>
  </TuningDetail>
  <TuningDetail>
    <BroadcastStandard>DvbS2</BroadcastStandard>
    <SatellitePosition>-275</SatellitePosition>
    <Frequency>3859000</Frequency>
    <SymbolRate>5250</SymbolRate>
    <Polarisation>CircularLeft</Polarisation>
    <ModulationScheme>Psk8</ModulationScheme>
    <FecCodeRate>Rate2_3</FecCodeRate>
    <PilotTonesState>On</PilotTonesState>
    <RollOffFactor>ThirtyFive</RollOffFactor>
    <StreamId>0</StreamId>
  </TuningDetail>
  <TuningDetail>
    <BroadcastStandard>DvbS</BroadcastStandard>
    <SatellitePosition>-275</SatellitePosition>
    <Frequency>3873000</Frequency>
    <SymbolRate>3200</SymbolRate>
    <Polarisation>CircularLeft</Polarisation>
    <ModulationScheme>Psk4</ModulationScheme>
    <FecCodeRate>Rate3_4</FecCodeRate>
  </TuningDetail>
  <TuningDetail>
    <BroadcastStandard>DvbS</BroadcastStandard>
    <SatellitePosition>-275</SatellitePosition>
    <Frequency>3902000</Frequency>
    <SymbolRate>1807</SymbolRate>
    <Polarisation>CircularRight</Polarisation>
    <ModulationScheme>Psk4</ModulationScheme>
    <FecCodeRate>Rate3_4</FecCodeRate>
  </TuningDetail>
  <TuningDetail>
    <BroadcastStandard>DvbS</BroadcastStandard>
    <SatellitePosition>-275</SatellitePosition>
    <Frequency>3936000</Frequency>
    <SymbolRate>4550</SymbolRate>
    <Polarisation>CircularRight</Polarisation>
    <ModulationScheme>Psk4</ModulationScheme>
    <FecCodeRate>Rate1_2</FecCodeRate>
  </TuningDetail>
  <TuningDetail>
    <BroadcastStandard>DvbS2</BroadcastStandard>
    <SatellitePosition>-275</SatellitePosition>
    <Frequency>3940000</Frequency>
    <SymbolRate>2400</SymbolRate>
    <Polarisation>CircularLeft</Polarisation>
    <ModulationScheme>Psk4</ModulationScheme>
    <FecCodeRate>Rate3_4</FecCodeRate>
    <PilotTonesState>Off</PilotTonesState>
    <RollOffFactor>ThirtyFive</RollOffFactor>
    <StreamId>0</StreamId>
  </TuningDetail>
  <TuningDetail>
    <BroadcastStandard>DvbS2</BroadcastStandard>
    <SatellitePosition>-275</SatellitePosition>
    <Frequency>3959000</Frequency>
    <SymbolRate>918</SymbolRate>
    <Polarisation>CircularLeft</Polarisation>
    <ModulationScheme>Psk8</ModulationScheme>
    <FecCodeRate>Rate3_4</FecCodeRate>
    <PilotTonesState>On</PilotTonesState>
    <RollOffFactor>ThirtyFive</RollOffFactor>
    <StreamId>0</StreamId>
  </TuningDetail>
  <TuningDetail>
    <BroadcastStandard>DvbS</BroadcastStandard>
    <SatellitePosition>-275</SatellitePosition>
    <Frequency>4003000</Frequency>
    <SymbolRate>5632</SymbolRate>
    <Polarisation>CircularLeft</Polarisation>
    <ModulationScheme>Psk4</ModulationScheme>
    <FecCodeRate>Rate3_4</FecCodeRate>
  </TuningDetail>
  <TuningDetail>
    <BroadcastStandard>DvbS</BroadcastStandard>
    <SatellitePosition>-275</SatellitePosition>
    <Frequency>4046000</Frequency>
    <SymbolRate>4800</SymbolRate>
    <Polarisation>CircularRight</Polarisation>
    <ModulationScheme>Psk4</ModulationScheme>
    <FecCodeRate>Rate3_4</FecCodeRate>
  </TuningDetail>
  <TuningDetail>
    <BroadcastStandard>DvbS2</BroadcastStandard>
    <SatellitePosition>-275</SatellitePosition>
    <Frequency>4054000</Frequency>
    <SymbolRate>4000</SymbolRate>
    <Polarisation>CircularRight</Polarisation>
    <ModulationScheme>Psk4</ModulationScheme>
    <FecCodeRate>Rate3_4</FecCodeRate>
    <PilotTonesState>Off</PilotTonesState>
    <RollOffFactor>ThirtyFive</RollOffFactor>
    <StreamId>0</StreamId>
  </TuningDetail>
  <TuningDetail>
    <BroadcastStandard>DvbS</BroadcastStandard>
    <SatellitePosition>-275</SatellitePosition>
    <Frequency>4110000</Frequency>
    <SymbolRate>1384</SymbolRate>
    <Polarisation>CircularLeft</Polarisation>
    <ModulationScheme>Psk4</ModulationScheme>
    <FecCodeRate>Rate3_4</FecCodeRate>
  </TuningDetail>
  <TuningDetail>
    <BroadcastStandard>DvbS</BroadcastStandard>
    <SatellitePosition>-275</SatellitePosition>
    <Frequency>4119000</Frequency>
    <SymbolRate>2893</SymbolRate>
    <Polarisation>CircularLeft</Polarisation>
    <ModulationScheme>Psk4</ModulationScheme>
    <FecCodeRate>Rate3_4</FecCodeRate>
  </TuningDetail>
  <TuningDetail>
    <BroadcastStandard>DvbS</BroadcastStandard>
    <SatellitePosition>-275</SatellitePosition>
    <Frequency>4151000</Frequency>
    <SymbolRate>1517</SymbolRate>
    <Polarisation>CircularLeft</Polarisation>
    <ModulationScheme>Psk4</ModulationScheme>
    <FecCodeRate>Rate3_4</FecCodeRate>
  </TuningDetail>
  <TuningDetail>
    <BroadcastStandard>DvbS2</BroadcastStandard>
    <SatellitePosition>-275</SatellitePosition>
    <Frequency>11018000</Frequency>
    <SymbolRate>2750</SymbolRate>
    <Polarisation>LinearVertical</Polarisation>
    <ModulationScheme>Psk8</ModulationScheme>
    <FecCodeRate>Rate2_3</FecCodeRate>
    <PilotTonesState>On</PilotTonesState>
    <RollOffFactor>ThirtyFive</RollOffFactor>
    <StreamId>0</StreamId>
  </TuningDetail>
  <TuningDetail>
    <BroadcastStandard>DvbS</BroadcastStandard>
    <SatellitePosition>-275</SatellitePosition>
    <Frequency>11050000</Frequency>
    <SymbolRate>17100</SymbolRate>
    <Polarisation>LinearHorizontal</Polarisation>
    <ModulationScheme>Psk4</ModulationScheme>
    <FecCodeRate>Rate7_8</FecCodeRate>
  </TuningDetail>
  <TuningDetail>
    <BroadcastStandard>DvbS</BroadcastStandard>
    <SatellitePosition>-275</SatellitePosition>
    <Frequency>11140000</Frequency>
    <SymbolRate>6620</SymbolRate>
    <Polarisation>LinearVertical</Polarisation>
    <ModulationScheme>Psk4</ModulationScheme>
    <FecCodeRate>Rate3_4</FecCodeRate>
  </TuningDetail>
  <TuningDetail>
    <BroadcastStandard>DvbS</BroadcastStandard>
    <SatellitePosition>-275</SatellitePosition>
    <Frequency>11151000</Frequency>
    <SymbolRate>5632</SymbolRate>
    <Polarisation>LinearVertical</Polarisation>
    <ModulationScheme>Psk4</ModulationScheme>
    <FecCodeRate>Rate3_4</FecCodeRate>
  </TuningDetail>
  <TuningDetail>
    <BroadcastStandard>DvbS</BroadcastStandard>
    <SatellitePosition>-275</SatellitePosition>
    <Frequency>11164000</Frequency>
    <SymbolRate>13333</SymbolRate>
    <Polarisation>LinearVertical</Polarisation>
    <ModulationScheme>Psk4</ModulationScheme>
    <FecCodeRate>Rate7_8</FecCodeRate>
  </TuningDetail>
  <TuningDetail>
    <BroadcastStandard>DvbS</BroadcastStandard>
    <SatellitePosition>-275</SatellitePosition>
    <Frequency>11182000</Frequency>
    <SymbolRate>13333</SymbolRate>
    <Polarisation>LinearVertical</Polarisation>
    <ModulationScheme>Psk4</ModulationScheme>
    <FecCodeRate>Rate7_8</FecCodeRate>
  </TuningDetail>
  <TuningDetail>
    <BroadcastStandard>DvbS2</BroadcastStandard>
    <SatellitePosition>-275</SatellitePosition>
    <Frequency>11495000</Frequency>
    <SymbolRate>44100</SymbolRate>
    <Polarisation>LinearVertical</Polarisation>
    <ModulationScheme>Psk4</ModulationScheme>
    <FecCodeRate>Rate9_10</FecCodeRate>
    <PilotTonesState>Off</PilotTonesState>
    <RollOffFactor>ThirtyFive</RollOffFactor>
    <StreamId>0</StreamId>
  </TuningDetail>
  <TuningDetail>
    <BroadcastStandard>DvbS</BroadcastStandard>
    <SatellitePosition>-275</SatellitePosition>
    <Frequency>11582000</Frequency>
    <SymbolRate>6620</SymbolRate>
    <Polarisation>LinearVertical</Polarisation>
    <ModulationScheme>Psk4</ModulationScheme>
    <FecCodeRate>Rate3_4</FecCodeRate>
  </TuningDetail>
  <TuningDetail>
    <BroadcastStandard>DvbS</BroadcastStandard>
    <SatellitePosition>-275</SatellitePosition>
    <Frequency>11609000</Frequency>
    <SymbolRate>5632</SymbolRate>
    <Polarisation>LinearVertical</Polarisation>
    <ModulationScheme>Psk4</ModulationScheme>
    <FecCodeRate>Rate3_4</FecCodeRate>
  </TuningDetail>
  <TuningDetail>
    <BroadcastStandard>DvbS</BroadcastStandard>
    <SatellitePosition>-275</SatellitePosition>
    <Frequency>11664000</Frequency>
    <SymbolRate>9766</SymbolRate>
    <Polarisation>LinearVertical</Polarisation>
    <ModulationScheme>Psk4</ModulationScheme>
    <FecCodeRate>Rate5_6</FecCodeRate>
  </TuningDetail>
  <TuningDetail>
    <BroadcastStandard>DvbS</BroadcastStandard>
    <SatellitePosition>-275</SatellitePosition>
    <Frequency>11688000</Frequency>
    <SymbolRate>5632</SymbolRate>
    <Polarisation>LinearVertical</Polarisation>
    <ModulationScheme>Psk4</ModulationScheme>
    <FecCodeRate>Rate3_4</FecCodeRate>
  </TuningDetail>
</ArrayOfTuningDetail>