<?xml version="1.0" encoding="utf-8"?>
<ArrayOfTuningDetail xmlns:xsi="http://www.w3.org/2001/XMLSchema-instance" xmlns:xsd="http://www.w3.org/2001/XMLSchema">
  <TuningDetail>
    <BroadcastStandard>DvbS</BroadcastStandard>
    <Longitude>-670</Longitude>
    <Frequency>11720000</Frequency>
    <Polarisation>LinearVertical</Polarisation>
    <ModulationScheme>Psk4</ModulationScheme>
    <SymbolRate>28888</SymbolRate>
    <FecCodeRate>Rate3_4</FecCodeRate>
  </TuningDetail>
  <TuningDetail>
    <BroadcastStandard>DvbS</BroadcastStandard>
    <Longitude>-670</Longitude>
    <Frequency>11760000</Frequency>
    <Polarisation>LinearVertical</Polarisation>
    <ModulationScheme>Psk4</ModulationScheme>
    <SymbolRate>28888</SymbolRate>
    <FecCodeRate>Rate3_4</FecCodeRate>
  </TuningDetail>
  <TuningDetail>
    <BroadcastStandard>DvbS</BroadcastStandard>
    <Longitude>-670</Longitude>
    <Frequency>11800000</Frequency>
    <Polarisation>LinearVertical</Polarisation>
    <ModulationScheme>Psk4</ModulationScheme>
    <SymbolRate>28888</SymbolRate>
    <FecCodeRate>Rate3_4</FecCodeRate>
  </TuningDetail>
  <TuningDetail>
    <BroadcastStandard>DvbS</BroadcastStandard>
    <Longitude>-670</Longitude>
    <Frequency>11840000</Frequency>
    <Polarisation>LinearVertical</Polarisation>
    <ModulationScheme>Psk4</ModulationScheme>
    <SymbolRate>28888</SymbolRate>
    <FecCodeRate>Rate3_4</FecCodeRate>
  </TuningDetail>
  <TuningDetail>
    <BroadcastStandard>DvbS</BroadcastStandard>
    <Longitude>-670</Longitude>
    <Frequency>11880000</Frequency>
    <Polarisation>LinearVertical</Polarisation>
    <ModulationScheme>Psk4</ModulationScheme>
    <SymbolRate>28888</SymbolRate>
    <FecCodeRate>Rate3_4</FecCodeRate>
  </TuningDetail>
  <TuningDetail>
    <BroadcastStandard>DvbS</BroadcastStandard>
    <Longitude>-670</Longitude>
    <Frequency>11920000</Frequency>
    <Polarisation>LinearVertical</Polarisation>
    <ModulationScheme>Psk4</ModulationScheme>
    <SymbolRate>28888</SymbolRate>
    <FecCodeRate>Rate3_4</FecCodeRate>
  </TuningDetail>
  <TuningDetail>
    <BroadcastStandard>DvbS</BroadcastStandard>
    <Longitude>-670</Longitude>
    <Frequency>12162000</Frequency>
    <Polarisation>LinearVertical</Polarisation>
    <ModulationScheme>Psk4</ModulationScheme>
    <SymbolRate>9600</SymbolRate>
    <FecCodeRate>Rate3_4</FecCodeRate>
  </TuningDetail>
</ArrayOfTuningDetail>