<?xml version="1.0" encoding="utf-8"?>
<ArrayOfTransponder xmlns:xsi="http://www.w3.org/2001/XMLSchema-instance" xmlns:xsd="http://www.w3.org/2001/XMLSchema">
  <Transponder>
    <CarrierFrequency>3553000</CarrierFrequency>
    <Polarisation>CircularL</Polarisation>
    <SymbolRate>20000</SymbolRate>
    <Modulation>ModNotSet</Modulation>
    <InnerFecRate>Rate3_4</InnerFecRate>
    <Pilot>NotSet</Pilot>
    <Rolloff>NotSet</Rolloff>
  </Transponder>
  <Transponder>
    <CarrierFrequency>3582000</CarrierFrequency>
    <Polarisation>CircularL</Polarisation>
    <SymbolRate>2850</SymbolRate>
    <Modulation>ModNotSet</Modulation>
    <InnerFecRate>Rate3_4</InnerFecRate>
    <Pilot>NotSet</Pilot>
    <Rolloff>NotSet</Rolloff>
  </Transponder>
  <Transponder>
    <CarrierFrequency>3588000</CarrierFrequency>
    <Polarisation>CircularL</Polarisation>
    <SymbolRate>4285</SymbolRate>
    <Modulation>ModNotSet</Modulation>
    <InnerFecRate>Rate3_4</InnerFecRate>
    <Pilot>NotSet</Pilot>
    <Rolloff>NotSet</Rolloff>
  </Transponder>
  <Transponder>
    <CarrierFrequency>3594000</CarrierFrequency>
    <Polarisation>CircularL</Polarisation>
    <SymbolRate>2850</SymbolRate>
    <Modulation>ModNotSet</Modulation>
    <InnerFecRate>Rate3_4</InnerFecRate>
    <Pilot>NotSet</Pilot>
    <Rolloff>NotSet</Rolloff>
  </Transponder>
  <Transponder>
    <CarrierFrequency>3600000</CarrierFrequency>
    <Polarisation>CircularL</Polarisation>
    <SymbolRate>5925</SymbolRate>
    <Modulation>ModNotSet</Modulation>
    <InnerFecRate>Rate3_4</InnerFecRate>
    <Pilot>NotSet</Pilot>
    <Rolloff>NotSet</Rolloff>
  </Transponder>
  <Transponder>
    <CarrierFrequency>3603000</CarrierFrequency>
    <Polarisation>CircularR</Polarisation>
    <SymbolRate>3300</SymbolRate>
    <Modulation>ModNotSet</Modulation>
    <InnerFecRate>Rate3_4</InnerFecRate>
    <Pilot>NotSet</Pilot>
    <Rolloff>NotSet</Rolloff>
  </Transponder>
  <Transponder>
    <CarrierFrequency>3605000</CarrierFrequency>
    <Polarisation>CircularL</Polarisation>
    <SymbolRate>2626</SymbolRate>
    <Modulation>ModNotSet</Modulation>
    <InnerFecRate>Rate3_4</InnerFecRate>
    <Pilot>NotSet</Pilot>
    <Rolloff>NotSet</Rolloff>
  </Transponder>
  <Transponder>
    <CarrierFrequency>3613000</CarrierFrequency>
    <Polarisation>CircularL</Polarisation>
    <SymbolRate>4285</SymbolRate>
    <Modulation>ModNotSet</Modulation>
    <InnerFecRate>Rate3_4</InnerFecRate>
    <Pilot>NotSet</Pilot>
    <Rolloff>NotSet</Rolloff>
  </Transponder>
  <Transponder>
    <CarrierFrequency>3617000</CarrierFrequency>
    <Polarisation>CircularR</Polarisation>
    <SymbolRate>1850</SymbolRate>
    <Modulation>ModNotSet</Modulation>
    <InnerFecRate>Rate3_4</InnerFecRate>
    <Pilot>NotSet</Pilot>
    <Rolloff>NotSet</Rolloff>
  </Transponder>
  <Transponder>
    <CarrierFrequency>3618000</CarrierFrequency>
    <Polarisation>CircularL</Polarisation>
    <SymbolRate>3038</SymbolRate>
    <Modulation>ModNotSet</Modulation>
    <InnerFecRate>Rate3_4</InnerFecRate>
    <Pilot>NotSet</Pilot>
    <Rolloff>NotSet</Rolloff>
  </Transponder>
  <Transponder>
    <CarrierFrequency>3623000</CarrierFrequency>
    <Polarisation>CircularL</Polarisation>
    <SymbolRate>4285</SymbolRate>
    <Modulation>ModNotSet</Modulation>
    <InnerFecRate>Rate3_4</InnerFecRate>
    <Pilot>NotSet</Pilot>
    <Rolloff>NotSet</Rolloff>
  </Transponder>
  <Transponder>
    <CarrierFrequency>3645000</CarrierFrequency>
    <Polarisation>CircularL</Polarisation>
    <SymbolRate>28000</SymbolRate>
    <Modulation>ModNotSet</Modulation>
    <InnerFecRate>Rate3_4</InnerFecRate>
    <Pilot>NotSet</Pilot>
    <Rolloff>NotSet</Rolloff>
  </Transponder>
  <Transponder>
    <CarrierFrequency>3675000</CarrierFrequency>
    <Polarisation>CircularL</Polarisation>
    <SymbolRate>17500</SymbolRate>
    <Modulation>ModNotSet</Modulation>
    <InnerFecRate>Rate3_4</InnerFecRate>
    <Pilot>NotSet</Pilot>
    <Rolloff>NotSet</Rolloff>
  </Transponder>
  <Transponder>
    <CarrierFrequency>3837000</CarrierFrequency>
    <Polarisation>CircularL</Polarisation>
    <SymbolRate>14815</SymbolRate>
    <Modulation>ModNotSet</Modulation>
    <InnerFecRate>Rate3_4</InnerFecRate>
    <Pilot>NotSet</Pilot>
    <Rolloff>NotSet</Rolloff>
  </Transponder>
  <Transponder>
    <CarrierFrequency>3908000</CarrierFrequency>
    <Polarisation>CircularL</Polarisation>
    <SymbolRate>2850</SymbolRate>
    <Modulation>ModNotSet</Modulation>
    <InnerFecRate>Rate3_4</InnerFecRate>
    <Pilot>NotSet</Pilot>
    <Rolloff>NotSet</Rolloff>
  </Transponder>
  <Transponder>
    <CarrierFrequency>3920000</CarrierFrequency>
    <Polarisation>CircularL</Polarisation>
    <SymbolRate>3000</SymbolRate>
    <Modulation>ModNotSet</Modulation>
    <InnerFecRate>Rate3_4</InnerFecRate>
    <Pilot>NotSet</Pilot>
    <Rolloff>NotSet</Rolloff>
  </Transponder>
  <Transponder>
    <CarrierFrequency>3924000</CarrierFrequency>
    <Polarisation>CircularL</Polarisation>
    <SymbolRate>2850</SymbolRate>
    <Modulation>ModNotSet</Modulation>
    <InnerFecRate>Rate3_4</InnerFecRate>
    <Pilot>NotSet</Pilot>
    <Rolloff>NotSet</Rolloff>
  </Transponder>
  <Transponder>
    <CarrierFrequency>10962000</CarrierFrequency>
    <Polarisation>LinearV</Polarisation>
    <SymbolRate>3290</SymbolRate>
    <Modulation>ModNotSet</Modulation>
    <InnerFecRate>Rate7_8</InnerFecRate>
    <Pilot>NotSet</Pilot>
    <Rolloff>NotSet</Rolloff>
  </Transponder>
  <Transponder>
    <CarrierFrequency>10972000</CarrierFrequency>
    <Polarisation>LinearH</Polarisation>
    <SymbolRate>11200</SymbolRate>
    <Modulation>ModNotSet</Modulation>
    <InnerFecRate>Rate3_4</InnerFecRate>
    <Pilot>NotSet</Pilot>
    <Rolloff>NotSet</Rolloff>
  </Transponder>
  <Transponder>
    <CarrierFrequency>11057000</CarrierFrequency>
    <Polarisation>LinearH</Polarisation>
    <SymbolRate>22222</SymbolRate>
    <Modulation>ModNotSet</Modulation>
    <InnerFecRate>Rate3_4</InnerFecRate>
    <Pilot>NotSet</Pilot>
    <Rolloff>NotSet</Rolloff>
  </Transponder>
  <Transponder>
    <CarrierFrequency>11305000</CarrierFrequency>
    <Polarisation>LinearV</Polarisation>
    <SymbolRate>30000</SymbolRate>
    <Modulation>ModNotSet</Modulation>
    <InnerFecRate>Rate7_8</InnerFecRate>
    <Pilot>NotSet</Pilot>
    <Rolloff>NotSet</Rolloff>
  </Transponder>
  <Transponder>
    <CarrierFrequency>11480000</CarrierFrequency>
    <Polarisation>LinearH</Polarisation>
    <SymbolRate>4020</SymbolRate>
    <Modulation>ModNotSet</Modulation>
    <InnerFecRate>Rate7_8</InnerFecRate>
    <Pilot>NotSet</Pilot>
    <Rolloff>NotSet</Rolloff>
  </Transponder>
  <Transponder>
    <CarrierFrequency>11501000</CarrierFrequency>
    <Polarisation>LinearV</Polarisation>
    <SymbolRate>3800</SymbolRate>
    <Modulation>ModNotSet</Modulation>
    <InnerFecRate>Rate1_2</InnerFecRate>
    <Pilot>NotSet</Pilot>
    <Rolloff>NotSet</Rolloff>
  </Transponder>
  <Transponder>
    <CarrierFrequency>11504000</CarrierFrequency>
    <Polarisation>LinearH</Polarisation>
    <SymbolRate>2080</SymbolRate>
    <Modulation>ModNotSet</Modulation>
    <InnerFecRate>Rate3_4</InnerFecRate>
    <Pilot>NotSet</Pilot>
    <Rolloff>NotSet</Rolloff>
  </Transponder>
  <Transponder>
    <CarrierFrequency>11524000</CarrierFrequency>
    <Polarisation>LinearV</Polarisation>
    <SymbolRate>1250</SymbolRate>
    <Modulation>ModNotSet</Modulation>
    <InnerFecRate>Rate7_8</InnerFecRate>
    <Pilot>NotSet</Pilot>
    <Rolloff>NotSet</Rolloff>
  </Transponder>
  <Transponder>
    <CarrierFrequency>11531000</CarrierFrequency>
    <Polarisation>LinearV</Polarisation>
    <SymbolRate>4280</SymbolRate>
    <Modulation>ModNotSet</Modulation>
    <InnerFecRate>Rate3_4</InnerFecRate>
    <Pilot>NotSet</Pilot>
    <Rolloff>NotSet</Rolloff>
  </Transponder>
  <Transponder>
    <CarrierFrequency>11565000</CarrierFrequency>
    <Polarisation>LinearV</Polarisation>
    <SymbolRate>1980</SymbolRate>
    <Modulation>ModNotSet</Modulation>
    <InnerFecRate>Rate3_4</InnerFecRate>
    <Pilot>NotSet</Pilot>
    <Rolloff>NotSet</Rolloff>
  </Transponder>
  <Transponder>
    <CarrierFrequency>11573000</CarrierFrequency>
    <Polarisation>LinearV</Polarisation>
    <SymbolRate>2500</SymbolRate>
    <Modulation>ModNotSet</Modulation>
    <InnerFecRate>Rate3_4</InnerFecRate>
    <Pilot>NotSet</Pilot>
    <Rolloff>NotSet</Rolloff>
  </Transponder>
  <Transponder>
    <CarrierFrequency>11649000</CarrierFrequency>
    <Polarisation>LinearH</Polarisation>
    <SymbolRate>2170</SymbolRate>
    <Modulation>ModNotSet</Modulation>
    <InnerFecRate>Rate3_4</InnerFecRate>
    <Pilot>NotSet</Pilot>
    <Rolloff>NotSet</Rolloff>
  </Transponder>
  <Transponder>
    <CarrierFrequency>11652000</CarrierFrequency>
    <Polarisation>LinearH</Polarisation>
    <SymbolRate>3000</SymbolRate>
    <Modulation>ModNotSet</Modulation>
    <InnerFecRate>Rate5_6</InnerFecRate>
    <Pilot>NotSet</Pilot>
    <Rolloff>NotSet</Rolloff>
  </Transponder>
  <Transponder>
    <CarrierFrequency>12718000</CarrierFrequency>
    <Polarisation>LinearV</Polarisation>
    <SymbolRate>27500</SymbolRate>
    <Modulation>ModNotSet</Modulation>
    <InnerFecRate>Rate3_4</InnerFecRate>
    <Pilot>NotSet</Pilot>
    <Rolloff>NotSet</Rolloff>
  </Transponder>
  <Transponder>
    <CarrierFrequency>3646000</CarrierFrequency>
    <Polarisation>CircularR</Polarisation>
    <SymbolRate>34170</SymbolRate>
    <Modulation>Mod16Apsk</Modulation>
    <InnerFecRate>Rate2_3</InnerFecRate>
    <Pilot>On</Pilot>
    <Rolloff>ThirtyFive</Rolloff>
  </Transponder>
  <Transponder>
    <CarrierFrequency>3781000</CarrierFrequency>
    <Polarisation>CircularR</Polarisation>
    <SymbolRate>10000</SymbolRate>
    <Modulation>Mod16Apsk</Modulation>
    <InnerFecRate>Rate3_4</InnerFecRate>
    <Pilot>On</Pilot>
    <Rolloff>ThirtyFive</Rolloff>
  </Transponder>
  <Transponder>
    <CarrierFrequency>3806000</CarrierFrequency>
    <Polarisation>CircularL</Polarisation>
    <SymbolRate>9000</SymbolRate>
    <Modulation>Mod16Apsk</Modulation>
    <InnerFecRate>Rate5_6</InnerFecRate>
    <Pilot>On</Pilot>
    <Rolloff>ThirtyFive</Rolloff>
  </Transponder>
  <Transponder>
    <CarrierFrequency>3820000</CarrierFrequency>
    <Polarisation>CircularL</Polarisation>
    <SymbolRate>13330</SymbolRate>
    <Modulation>Mod16Apsk</Modulation>
    <InnerFecRate>Rate5_6</InnerFecRate>
    <Pilot>On</Pilot>
    <Rolloff>ThirtyFive</Rolloff>
  </Transponder>
  <Transponder>
    <CarrierFrequency>3942000</CarrierFrequency>
    <Polarisation>CircularL</Polarisation>
    <SymbolRate>12150</SymbolRate>
    <Modulation>Mod32Apsk</Modulation>
    <InnerFecRate>Rate3_4</InnerFecRate>
    <Pilot>On</Pilot>
    <Rolloff>ThirtyFive</Rolloff>
  </Transponder>
  <Transponder>
    <CarrierFrequency>3978000</CarrierFrequency>
    <Polarisation>CircularL</Polarisation>
    <SymbolRate>27000</SymbolRate>
    <Modulation>Mod32Apsk</Modulation>
    <InnerFecRate>Rate3_4</InnerFecRate>
    <Pilot>On</Pilot>
    <Rolloff>ThirtyFive</Rolloff>
  </Transponder>
  <Transponder>
    <CarrierFrequency>4026000</CarrierFrequency>
    <Polarisation>CircularL</Polarisation>
    <SymbolRate>14990</SymbolRate>
    <Modulation>Mod8Psk</Modulation>
    <InnerFecRate>Rate3_5</InnerFecRate>
    <Pilot>On</Pilot>
    <Rolloff>ThirtyFive</Rolloff>
  </Transponder>
  <Transponder>
    <CarrierFrequency>4046000</CarrierFrequency>
    <Polarisation>CircularL</Polarisation>
    <SymbolRate>15284</SymbolRate>
    <Modulation>Mod8Psk</Modulation>
    <InnerFecRate>Rate3_4</InnerFecRate>
    <Pilot>On</Pilot>
    <Rolloff>ThirtyFive</Rolloff>
  </Transponder>
  <Transponder>
    <CarrierFrequency>4106000</CarrierFrequency>
    <Polarisation>CircularR</Polarisation>
    <SymbolRate>14990</SymbolRate>
    <Modulation>Mod8Psk</Modulation>
    <InnerFecRate>Rate3_4</InnerFecRate>
    <Pilot>On</Pilot>
    <Rolloff>ThirtyFive</Rolloff>
  </Transponder>
  <Transponder>
    <CarrierFrequency>4124000</CarrierFrequency>
    <Polarisation>CircularL</Polarisation>
    <SymbolRate>14990</SymbolRate>
    <Modulation>Mod8Psk</Modulation>
    <InnerFecRate>Rate3_4</InnerFecRate>
    <Pilot>On</Pilot>
    <Rolloff>ThirtyFive</Rolloff>
  </Transponder>
  <Transponder>
    <CarrierFrequency>4126000</CarrierFrequency>
    <Polarisation>CircularR</Polarisation>
    <SymbolRate>15284</SymbolRate>
    <Modulation>Mod8Psk</Modulation>
    <InnerFecRate>Rate3_4</InnerFecRate>
    <Pilot>On</Pilot>
    <Rolloff>ThirtyFive</Rolloff>
  </Transponder>
  <Transponder>
    <CarrierFrequency>4144000</CarrierFrequency>
    <Polarisation>CircularL</Polarisation>
    <SymbolRate>14990</SymbolRate>
    <Modulation>Mod8Psk</Modulation>
    <InnerFecRate>Rate3_4</InnerFecRate>
    <Pilot>On</Pilot>
    <Rolloff>ThirtyFive</Rolloff>
  </Transponder>
  <Transponder>
    <CarrierFrequency>10910000</CarrierFrequency>
    <Polarisation>LinearV</Polarisation>
    <SymbolRate>6172</SymbolRate>
    <Modulation>Mod8Psk</Modulation>
    <InnerFecRate>Rate3_4</InnerFecRate>
    <Pilot>On</Pilot>
    <Rolloff>ThirtyFive</Rolloff>
  </Transponder>
  <Transponder>
    <CarrierFrequency>11165000</CarrierFrequency>
    <Polarisation>LinearH</Polarisation>
    <SymbolRate>25000</SymbolRate>
    <Modulation>Mod8Psk</Modulation>
    <InnerFecRate>Rate2_3</InnerFecRate>
    <Pilot>On</Pilot>
    <Rolloff>ThirtyFive</Rolloff>
  </Transponder>
  <Transponder>
    <CarrierFrequency>11241000</CarrierFrequency>
    <Polarisation>LinearV</Polarisation>
    <SymbolRate>2740</SymbolRate>
    <Modulation>Mod8Psk</Modulation>
    <InnerFecRate>Rate3_4</InnerFecRate>
    <Pilot>On</Pilot>
    <Rolloff>ThirtyFive</Rolloff>
  </Transponder>
  <Transponder>
    <CarrierFrequency>11265000</CarrierFrequency>
    <Polarisation>LinearH</Polarisation>
    <SymbolRate>30000</SymbolRate>
    <Modulation>Mod8Psk</Modulation>
    <InnerFecRate>Rate3_4</InnerFecRate>
    <Pilot>On</Pilot>
    <Rolloff>ThirtyFive</Rolloff>
  </Transponder>
  <Transponder>
    <CarrierFrequency>11299000</CarrierFrequency>
    <Polarisation>LinearH</Polarisation>
    <SymbolRate>20000</SymbolRate>
    <Modulation>ModQpsk</Modulation>
    <InnerFecRate>Rate3_4</InnerFecRate>
    <Pilot>Off</Pilot>
    <Rolloff>ThirtyFive</Rolloff>
  </Transponder>
  <Transponder>
    <CarrierFrequency>11345000</CarrierFrequency>
    <Polarisation>LinearH</Polarisation>
    <SymbolRate>27500</SymbolRate>
    <Modulation>ModQpsk</Modulation>
    <InnerFecRate>Rate3_4</InnerFecRate>
    <Pilot>Off</Pilot>
    <Rolloff>ThirtyFive</Rolloff>
  </Transponder>
  <Transponder>
    <CarrierFrequency>11385000</CarrierFrequency>
    <Polarisation>LinearH</Polarisation>
    <SymbolRate>30000</SymbolRate>
    <Modulation>Mod8Psk</Modulation>
    <InnerFecRate>Rate3_4</InnerFecRate>
    <Pilot>On</Pilot>
    <Rolloff>ThirtyFive</Rolloff>
  </Transponder>
  <Transponder>
    <CarrierFrequency>11425000</CarrierFrequency>
    <Polarisation>LinearV</Polarisation>
    <SymbolRate>32730</SymbolRate>
    <Modulation>ModQpsk</Modulation>
    <InnerFecRate>Rate3_4</InnerFecRate>
    <Pilot>Off</Pilot>
    <Rolloff>ThirtyFive</Rolloff>
  </Transponder>
  <Transponder>
    <CarrierFrequency>11471000</CarrierFrequency>
    <Polarisation>LinearV</Polarisation>
    <SymbolRate>11160</SymbolRate>
    <Modulation>Mod8Psk</Modulation>
    <InnerFecRate>Rate2_3</InnerFecRate>
    <Pilot>On</Pilot>
    <Rolloff>ThirtyFive</Rolloff>
  </Transponder>
  <Transponder>
    <CarrierFrequency>11485000</CarrierFrequency>
    <Polarisation>LinearV</Polarisation>
    <SymbolRate>12222</SymbolRate>
    <Modulation>Mod8Psk</Modulation>
    <InnerFecRate>Rate5_6</InnerFecRate>
    <Pilot>On</Pilot>
    <Rolloff>ThirtyFive</Rolloff>
  </Transponder>
  <Transponder>
    <CarrierFrequency>11490000</CarrierFrequency>
    <Polarisation>LinearH</Polarisation>
    <SymbolRate>7243</SymbolRate>
    <Modulation>Mod32Apsk</Modulation>
    <InnerFecRate>Rate3_4</InnerFecRate>
    <Pilot>On</Pilot>
    <Rolloff>ThirtyFive</Rolloff>
  </Transponder>
  <Transponder>
    <CarrierFrequency>11512000</CarrierFrequency>
    <Polarisation>LinearH</Polarisation>
    <SymbolRate>6160</SymbolRate>
    <Modulation>ModQpsk</Modulation>
    <InnerFecRate>Rate1_4</InnerFecRate>
    <Pilot>Off</Pilot>
    <Rolloff>ThirtyFive</Rolloff>
  </Transponder>
  <Transponder>
    <CarrierFrequency>11580000</CarrierFrequency>
    <Polarisation>LinearH</Polarisation>
    <SymbolRate>30000</SymbolRate>
    <Modulation>Mod32Apsk</Modulation>
    <InnerFecRate>Rate1_3</InnerFecRate>
    <Pilot>On</Pilot>
    <Rolloff>ThirtyFive</Rolloff>
  </Transponder>
  <Transponder>
    <CarrierFrequency>11668000</CarrierFrequency>
    <Polarisation>LinearH</Polarisation>
    <SymbolRate>14400</SymbolRate>
    <Modulation>Mod8Psk</Modulation>
    <InnerFecRate>Rate5_6</InnerFecRate>
    <Pilot>On</Pilot>
    <Rolloff>ThirtyFive</Rolloff>
  </Transponder>
  <Transponder>
    <CarrierFrequency>11674000</CarrierFrequency>
    <Polarisation>LinearV</Polarisation>
    <SymbolRate>7800</SymbolRate>
    <Modulation>Mod8Psk</Modulation>
    <InnerFecRate>Rate5_6</InnerFecRate>
    <Pilot>On</Pilot>
    <Rolloff>ThirtyFive</Rolloff>
  </Transponder>
  <Transponder>
    <CarrierFrequency>12505000</CarrierFrequency>
    <Polarisation>LinearV</Polarisation>
    <SymbolRate>2020</SymbolRate>
    <Modulation>Mod8Psk</Modulation>
    <InnerFecRate>Rate3_4</InnerFecRate>
    <Pilot>On</Pilot>
    <Rolloff>ThirtyFive</Rolloff>
  </Transponder>
  <Transponder>
    <CarrierFrequency>12519000</CarrierFrequency>
    <Polarisation>LinearH</Polarisation>
    <SymbolRate>5000</SymbolRate>
    <Modulation>Mod8Psk</Modulation>
    <InnerFecRate>Rate3_4</InnerFecRate>
    <Pilot>On</Pilot>
    <Rolloff>ThirtyFive</Rolloff>
  </Transponder>
  <Transponder>
    <CarrierFrequency>12538000</CarrierFrequency>
    <Polarisation>LinearV</Polarisation>
    <SymbolRate>16317</SymbolRate>
    <Modulation>ModQpsk</Modulation>
    <InnerFecRate>Rate3_4</InnerFecRate>
    <Pilot>Off</Pilot>
    <Rolloff>ThirtyFive</Rolloff>
  </Transponder>
  <Transponder>
    <CarrierFrequency>12602000</CarrierFrequency>
    <Polarisation>LinearH</Polarisation>
    <SymbolRate>5000</SymbolRate>
    <Modulation>Mod8Psk</Modulation>
    <InnerFecRate>Rate3_4</InnerFecRate>
    <Pilot>On</Pilot>
    <Rolloff>ThirtyFive</Rolloff>
  </Transponder>
</ArrayOfTransponder>