<?xml version="1.0" encoding="utf-8" standalone="yes"?>
<!--version="1.0" encoding="utf-8" standalone="yes"-->
<window>
  <id>2010</id>
  <defaultcontrol>12</defaultcontrol>
  <allowoverlay>no</allowoverlay>
  <controls>
    <control>
      <type>image</type>
      <id>0</id>
      <width>1920</width>
      <height>1080</height>
      <texture>white.png</texture>
      <colordiffuse>50005eef</colordiffuse>
    </control>
    <control>
      <description>background image</description>
      <type>image</type>
      <id>0</id>
      <posX>279</posX>
      <width>1455</width>
      <height>517</height>
      <posY>289</posY>
      <texture>dialog_schedule_rec.png</texture>
    </control>
    <control>
      <description>Channel</description>
      <type>label</type>
      <id>0</id>
      <posX>399</posX>
      <posY>424</posY>
      <label>602</label>
      <font>font13</font>
      <textcolor>ffffd700</textcolor>
    </control>
    <control>
      <description>Channel Select</description>
      <type>spincontrol</type>
      <id>1</id>
      <posX>639</posX>
      <posY>430</posY>
      <showrange>no</showrange>
      <digits>3</digits>
      <onup>12</onup>
      <ondown>2</ondown>
      <onleft>1</onleft>
      <onright>1</onright>
      <textcolor>ffffd700</textcolor>
    </control>
    <control>
      <description>Start Date/Time</description>
      <type>label</type>
      <id>0</id>
      <posX>399</posX>
      <posY>487</posY>
      <label>633</label>
      <font>font13</font>
      <textcolor>ffffd700</textcolor>
    </control>
    <control>
      <description>Time</description>
      <type>label</type>
      <id>0</id>
      <posX>399</posX>
      <posY>525</posY>
      <label>635</label>
      <font>font13</font>
      <textcolor>ffffd700</textcolor>
    </control>
    <control>
      <description>time hours</description>
      <type>spincontrol</type>
      <spintype>int</spintype>
      <orientation>vertical</orientation>
      <digits>2</digits>
      <id>2</id>
      <posX>453</posX>
      <posY>571</posY>
      <showrange>no</showrange>
      <onup>1</onup>
      <ondown>4</ondown>
      <onleft>2</onleft>
      <onright>3</onright>
      <textcolor>ffffd700</textcolor>
      <textureUp>arrow_round_up_nofocus.png</textureUp>
      <textureDown>arrow_round_down_nofocus.png</textureDown>
      <textureUpFocus>arrow_round_up_focus.png</textureUpFocus>
      <textureDownFocus>arrow_round_down_focus.png</textureDownFocus>
    </control>
    <control>
      <description>time minutes</description>
      <type>spincontrol</type>
      <spintype>int</spintype>
      <orientation>vertical</orientation>
      <digits>2</digits>
      <id>3</id>
      <posX>586</posX>
      <posY>571</posY>
      <showrange>no</showrange>
      <onup>2</onup>
      <ondown>4</ondown>
      <onleft>2</onleft>
      <onright>3</onright>
      <textcolor>ffffd700</textcolor>
      <textureUp>arrow_round_up_nofocus.png</textureUp>
      <textureDown>arrow_round_down_nofocus.png</textureDown>
      <textureUpFocus>arrow_round_up_focus.png</textureUpFocus>
      <textureDownFocus>arrow_round_down_focus.png</textureDownFocus>
    </control>
    <control>
      <description>Date</description>
      <type>label</type>
      <id>0</id>
      <posX>399</posX>
      <posY>618</posY>
      <label>636</label>
      <font>font13</font>
      <textcolor>ffffd700</textcolor>
    </control>
    <control>
      <description>DD</description>
      <type>spincontrol</type>
      <spintype>int</spintype>
      <orientation>vertical</orientation>
      <id>4</id>
      <posX>453</posX>
      <posY>675</posY>
      <showrange>no</showrange>
      <onup>2</onup>
      <ondown>7</ondown>
      <onleft>4</onleft>
      <onright>5</onright>
      <textcolor>ffffd700</textcolor>
      <textureUp>arrow_round_up_nofocus.png</textureUp>
      <textureDown>arrow_round_down_nofocus.png</textureDown>
      <textureUpFocus>arrow_round_up_focus.png</textureUpFocus>
      <textureDownFocus>arrow_round_down_focus.png</textureDownFocus>
    </control>
    <control>
      <description>MM</description>
      <type>spincontrol</type>
      <spintype>int</spintype>
      <orientation>vertical</orientation>
      <id>5</id>
      <posX>586</posX>
      <posY>675</posY>
      <showrange>no</showrange>
      <onup>2</onup>
      <ondown>7</ondown>
      <onleft>4</onleft>
      <onright>6</onright>
      <textcolor>ffffd700</textcolor>
      <textureUp>arrow_round_up_nofocus.png</textureUp>
      <textureDown>arrow_round_down_nofocus.png</textureDown>
      <textureUpFocus>arrow_round_up_focus.png</textureUpFocus>
      <textureDownFocus>arrow_round_down_focus.png</textureDownFocus>
    </control>
    <control>
      <description>YYYY</description>
      <type>spincontrol</type>
      <spintype>int</spintype>
      <digits>4</digits>
      <orientation>vertical</orientation>
      <id>6</id>
      <posX>720</posX>
      <posY>675</posY>
      <showrange>no</showrange>
      <onup>2</onup>
      <ondown>7</ondown>
      <onleft>5</onleft>
      <onright>7</onright>
      <textcolor>ffffd700</textcolor>
      <textureUp>arrow_round_up_nofocus.png</textureUp>
      <textureDown>arrow_round_down_nofocus.png</textureDown>
      <textureUpFocus>arrow_round_up_focus.png</textureUpFocus>
      <textureDownFocus>arrow_round_down_focus.png</textureDownFocus>
    </control>
    <control>
      <description>End Date/Time</description>
      <type>label</type>
      <id>0</id>
      <posX>960</posX>
      <posY>487</posY>
      <label>634</label>
      <font>font13</font>
      <textcolor>ffffd700</textcolor>
    </control>
    <control>
      <description>Time</description>
      <type>label</type>
      <id>0</id>
      <posX>960</posX>
      <posY>525</posY>
      <label>635</label>
      <font>font13</font>
      <textcolor>ffffd700</textcolor>
    </control>
    <control>
      <description>time hours</description>
      <type>spincontrol</type>
      <spintype>int</spintype>
      <orientation>vertical</orientation>
      <digits>2</digits>
      <id>7</id>
      <posX>1012</posX>
      <posY>571</posY>
      <showrange>no</showrange>
      <onup>4</onup>
      <ondown>9</ondown>
      <onleft>7</onleft>
      <onright>8</onright>
      <textcolor>ffffd700</textcolor>
      <textureUp>arrow_round_up_nofocus.png</textureUp>
      <textureDown>arrow_round_down_nofocus.png</textureDown>
      <textureUpFocus>arrow_round_up_focus.png</textureUpFocus>
      <textureDownFocus>arrow_round_down_focus.png</textureDownFocus>
    </control>
    <control>
      <description>time minutes</description>
      <type>spincontrol</type>
      <spintype>int</spintype>
      <orientation>vertical</orientation>
      <digits>2</digits>
      <id>8</id>
      <posX>1146</posX>
      <posY>571</posY>
      <showrange>no</showrange>
      <onup>4</onup>
      <ondown>9</ondown>
      <onleft>7</onleft>
      <onright>9</onright>
      <textcolor>ffffd700</textcolor>
      <textureUp>arrow_round_up_nofocus.png</textureUp>
      <textureDown>arrow_round_down_nofocus.png</textureDown>
      <textureUpFocus>arrow_round_up_focus.png</textureUpFocus>
      <textureDownFocus>arrow_round_down_focus.png</textureDownFocus>
    </control>
    <control>
      <description>Date</description>
      <type>label</type>
      <id>0</id>
      <posX>960</posX>
      <posY>618</posY>
      <label>636</label>
      <font>font13</font>
      <textcolor>ffffd700</textcolor>
    </control>
    <control>
      <description>DD</description>
      <type>spincontrol</type>
      <spintype>int</spintype>
      <orientation>vertical</orientation>
      <id>9</id>
      <posX>1012</posX>
      <posY>675</posY>
      <showrange>no</showrange>
      <onup>7</onup>
      <ondown>12</ondown>
      <onleft>9</onleft>
      <onright>10</onright>
      <textcolor>ffffd700</textcolor>
      <textureUp>arrow_round_up_nofocus.png</textureUp>
      <textureDown>arrow_round_down_nofocus.png</textureDown>
      <textureUpFocus>arrow_round_up_focus.png</textureUpFocus>
      <textureDownFocus>arrow_round_down_focus.png</textureDownFocus>
    </control>
    <control>
      <description>MM</description>
      <type>spincontrol</type>
      <spintype>int</spintype>
      <orientation>vertical</orientation>
      <id>10</id>
      <posX>1146</posX>
      <posY>675</posY>
      <showrange>no</showrange>
      <onup>7</onup>
      <ondown>12</ondown>
      <onleft>9</onleft>
      <onright>11</onright>
      <textcolor>ffffd700</textcolor>
      <textureUp>arrow_round_up_nofocus.png</textureUp>
      <textureDown>arrow_round_down_nofocus.png</textureDown>
      <textureUpFocus>arrow_round_up_focus.png</textureUpFocus>
      <textureDownFocus>arrow_round_down_focus.png</textureDownFocus>
    </control>
    <control>
      <description>YYYY</description>
      <type>spincontrol</type>
      <spintype>int</spintype>
      <digits>4</digits>
      <orientation>vertical</orientation>
      <id>11</id>
      <posX>1279</posX>
      <posY>675</posY>
      <showrange>no</showrange>
      <onup>7</onup>
      <ondown>12</ondown>
      <onleft>10</onleft>
      <onright>11</onright>
      <textcolor>ffffd700</textcolor>
      <textureUp>arrow_round_up_nofocus.png</textureUp>
      <textureDown>arrow_round_down_nofocus.png</textureDown>
      <textureUpFocus>arrow_round_up_focus.png</textureUpFocus>
      <textureDownFocus>arrow_round_down_focus.png</textureDownFocus>
    </control>
    <control>
      <description>OK button</description>
      <type>button</type>
      <id>12</id>
      <posX>1527</posX>
      <posY>343</posY>
      <width>45</width>
      <height>45</height>
      <textureFocus>tb_exit.png</textureFocus>
      <textureNoFocus>tb_exitNF.png</textureNoFocus>
      <label>-</label>
      <onleft>10</onleft>
      <onright>10</onright>
      <onup>11</onup>
      <ondown>1</ondown>
    </control>
    <control>
      <description>dialog Heading</description>
      <type>label</type>
      <id>13</id>
      <posX>399</posX>
      <posY>355</posY>
      <label>0</label>
      <font>font13</font>
      <textcolor>ffffd700</textcolor>
    </control>
  </controls>
</window>