<?xml version="1.0" encoding="utf-8" standalone="yes"?>
<!--version="1.0" encoding="utf-8" standalone="yes"-->
<window>
  <id>112012</id>
  <defaultcontrol>2</defaultcontrol>
  <allowoverlay>[facadeview.playlist|facadeview.coverflow | facadeview.smallicons | facadeview.largeicons]</allowoverlay>
  <define>#useSelectedFanart:Yes</define>
  <controls>
    <control>
      <description>Main Background</description>
      <type>image</type>
      <id>1</id>
      <texture>BH Musicvideos.jpg</texture>
      <width>1920</width>
      <height>1080</height>
      <animation effect="fade" time="70" reversible="false">visible</animation>
    </control>
    <import>common.time.xml</import>
    <import>common.music.fanart.xml</import>
    <control>
      <description>General Overlay</description>
      <id>0</id>
      <type>image</type>
      <posX>0</posX>
      <posY>45</posY>
      <width>1920</width>
      <height>1080</height>
      <texture>general_overlay.png</texture>
    </control>
    <control>
      <type>fadelabel</type>
      <description>mvCentral Title</description>
      <id>0</id>
      <posX>90</posX>
      <posY>40</posY>
      <width>1200</width>
      <font>Menutitle</font>
      <align>left</align>
      <visible>yes</visible>
      <textcolor>ffffd700</textcolor>
      <label>mvCentral  -  #mvCentral.Hierachy</label>
      <animation effect="fade" time="70" reversible="false">visible</animation>
    </control>
    <control>
      <description>Number of Files Label</description>
      <type>label</type>
      <id>1</id>
      <posX>1866</posX>
      <posY>93</posY>
      <label>#selectedindex/#mvCentral.Playlist.Count #mvCentral.Translation.Videos.Label</label>
      <align>right</align>
      <textcolor>ffffd700</textcolor>
      <font>font12</font>
      <animation effect="fade" time="70" reversible="false">visible</animation>
    </control>
    <control>
      <description>Total Duration for tracks by artist</description>
      <type>label</type>
      <id>1</id>
      <posX>1866</posX>
      <posY>135</posY>
      <label>Playlist #mvCentral.Translation.Runtime.Label #mvCentral.Playlist.Runtime</label>
      <align>right</align>
      <textcolor>ffffd700</textcolor>
      <font>font12</font>
      <animation effect="fade" time="70" reversible="false">visible</animation>
    </control>
    <!-- ************************************ -->
    <!--          Selected Item Image         -->
    <!-- ************************************ -->
    <control>
      <id>0</id>
      <type>image</type>
      <visible>[facadeview.playlist | facadeview.filmstrip | facadeview.smallicons | facadeview.largeicons]</visible>
      <posX>57</posX>
      <posY>315</posY>
      <width>420</width>
      <height>333</height>
      <texture flipY="true" diffuse="Thumb_Mask.png">#mvCentral.VideoImage</texture>
      <animation effect="fade" time="70" reversible="false">visible</animation>
      <keepaspectratio>yes</keepaspectratio>
      <animation effect="fade" time="70" reversible="false">visible</animation>
    </control>
    <!-- **************************************** -->
    <!--       Selected Item Information          -->
    <!-- **************************************** -->
    <control>
      <id>0</id>
      <description>Artist Name</description>
      <type>fadelabel</type>
      <posX>60</posX>
      <posY>232</posY>
      <width>1387</width>
      <font>font18</font>
      <label>#mvCentral.ArtistName</label>
      <animation effect="fade" time="70" reversible="false">visible</animation>
    </control>
    <control>
      <id>0</id>
      <description>Track Description</description>
      <type>textboxscrollup</type>
      <posX>495</posX>
      <posY>315</posY>
      <width>525</width>
      <height>592</height>
      <label>#mvCentral.Description</label>
      <seperator>-----------------------------------------------------------------------------------</seperator>
      <font>font10</font>
      <scrollStartDelaySec>10</scrollStartDelaySec>
      <visible>[facadeview.playlist | facadeview.smallicons | facadeview.largeicons]+!string.starts(#mvCentral.Description,#)</visible>
      <animation effect="fade" time="70" reversible="false">visible</animation>
    </control>
    <control>
      <id>0</id>
      <description>Track Description</description>
      <type>textboxscrollup</type>
      <posX>525</posX>
      <posY>315</posY>
      <width>1200</width>
      <height>435</height>
      <label>#mvCentral.Description</label>
      <seperator>-----------------------------------------------------------------------------------</seperator>
      <font>font12</font>
      <scrollStartDelaySec>10</scrollStartDelaySec>
      <visible>[facadeview.filmstrip]</visible>
      <animation effect="fade" time="70" reversible="false">visible</animation>
    </control>
    <!-- ************************************ -->
    <!--              Hidden Menu             -->
    <!-- ************************************ -->
    <control>
      <type>actiongroup</type>
      <description>action menu</description>
      <defaultcontrol>2</defaultcontrol>
      <onexit>50</onexit>
      <buttonX>0</buttonX>
      <buttonY>0</buttonY>
      <buttonwidth>159</buttonwidth>
      <buttonheight>1080</buttonheight>
      <textureFocus>-</textureFocus>
      <textureNoFocus>Action_nofocus.png</textureNoFocus>
      <width>412</width>
      <height>1350</height>
      <dimColor>00ffffff</dimColor>
      <animation effect="slide" time="70" start="-300,0" reversible="false">visible</animation>
      <visible>!Control.HasFocus(50)</visible>
      <control>
        <type>image</type>
        <id>1</id>
        <width>1920</width>
        <height>1080</height>
        <texture>white.png</texture>
        <colordiffuse>50005eef</colordiffuse>
      </control>
      <control>
        <type>image</type>
        <posX>39</posX>
        <posY>117</posY>
        <width>550</width>
        <height>886</height>
        <texture>Backslide.png</texture>
        <colorDiffuse>fffffffff</colorDiffuse>
        <visible>!Control.HasFocus(50)</visible>
        <animation effect="slide" time="70" start="-300,0" reversible="false">visible</animation>
        <animation effect="slide" time="70" end="-300,0" reversible="false">hidden</animation>
      </control>
      <control>
        <description>group element</description>
        <type>group</type>
        <posX>106</posX>
        <posY>181</posY>
        <layout>StackLayout</layout>
        <animation effect="slide" time="70" start="-300,0" reversible="false">visible</animation>
        <animation effect="slide" time="70" end="-300,0" reversible="false">hidden</animation>
        <visible>!Control.HasFocus(50)</visible>
        <control>
          <description>View-As button</description>
          <type>menubutton</type>
          <id>2</id>
          <label />
          <mode>dialoglist</mode>
          <valueTextInButton>yes</valueTextInButton>
          <valuePrefixText>97</valuePrefixText>
          <onright>50</onright>
          <onup>17</onup>
          <ondown>20</ondown>
        </control>
        <control>
          <description>Shuffle button</description>
          <type>button</type>
          <id>20</id>
          <label>191</label>
          <onleft>50</onleft>
        </control>
        <control>
          <description>Repeat on/off button</description>
          <type>checkbutton</type>
          <id>30</id>
          <label>486</label>
          <onleft>50</onleft>
        </control>
        <control>
          <description>AutoPlay on/off button</description>
          <type>checkbutton</type>
          <id>40</id>
          <label>Auto Play</label>
          <onleft>50</onleft>
        </control>
        <control>
          <description>Load button</description>
          <type>button</type>
          <id>9</id>
          <label>607</label>
          <onleft>50</onleft>
        </control>
        <control>
          <description>Save button</description>
          <type>button</type>
          <id>21</id>
          <label>190</label>
          <onleft>50</onleft>
        </control>
        <control>
          <description>Clear button</description>
          <type>button</type>
          <id>22</id>
          <label>192</label>
          <onleft>50</onleft>
        </control>
        <control>
          <description>Play button</description>
          <type>button</type>
          <id>23</id>
          <label>208</label>
          <onleft>50</onleft>
        </control>
        <control>
          <description>Next button</description>
          <type>button</type>
          <id>24</id>
          <label>209</label>
          <onleft>50</onleft>
        </control>
        <control>
          <description>Previous button</description>
          <type>button</type>
          <id>25</id>
          <label>210</label>
          <onleft>50</onleft>
        </control>
      </control>
    </control>
    <!-- ****************************************************************************** -->
    <!--     Facade Layout Controls, List, Icons, Filmstrip, Coverflow and Playlist     -->
    <!-- ****************************************************************************** -->
    <control>
      <description>group element</description>
      <type>group</type>
      <visible>!Control.HasFocus(50)</visible>
      <animation effect="slide" time="70" start="0,-300">WindowOpen</animation>
      <animation effect="slide" time="70" end="800,0">WindowClose</animation>
      <control>
        <description>composite control consisting of a list control and a thumbnail panel</description>
        <type>facadeview</type>
        <id>50</id>
        <control style="NoShadow">
          <description>listcontrol</description>
          <type>listcontrol</type>
          <id>50</id>
          <onleft>2</onleft>
          <onright>2</onright>
          <scrollOffset>2</scrollOffset>
          <unfocusedAlpha>160</unfocusedAlpha>
        </control>
        <control>
          <description>playlist listcontrol</description>
          <type>playlistcontrol</type>
          <id>50</id>
          <posX>1020</posX>
          <posY>315</posY>
          <width>1140</width>
          <height>675</height>
          <font>font11</font>
          <onleft>2</onleft>
          <onright>2</onright>
          <upBtnWidth>48</upBtnWidth>
          <downBtnWidth>48</downBtnWidth>
          <deleteBtnWidth>55</deleteBtnWidth>
          <upBtnHeight>45</upBtnHeight>
          <downBtnHeight>45</downBtnHeight>
          <deleteBtnHeight>45</deleteBtnHeight>
          <upBtnXOffset>679</upBtnXOffset>
          <downBtnXOffset>748</downBtnXOffset>
          <deleteBtnXOffset>817</deleteBtnXOffset>
          <scrollOffset>2</scrollOffset>
          <itemWidth>36</itemWidth>
          <itemHeight>36</itemHeight>
          <IconXOff>18</IconXOff>
          <IconYOff>6</IconYOff>
        </control>
        <control>
          <description>Thumbnail Panel</description>
          <type>thumbnailpanel</type>
          <dimColor>90ffffff</dimColor>
          <id>50</id>
          <posX>1035</posX>
          <posY>240</posY>
          <width>900</width>
          <height>822</height>
          <scrollOffset>0</scrollOffset>
          <onleft>2</onleft>
          <onright>2</onright>
          <textureWidthBig>232</textureWidthBig>
          <textureHeightBig>232</textureHeightBig>
          <itemWidthBig>286</itemWidthBig>
          <itemHeightBig>322</itemHeightBig>
          <itemWidth>217</itemWidth>
          <itemHeight>247</itemHeight>
          <thumbWidthBig>232</thumbWidthBig>
          <thumbHeightBig>232</thumbHeightBig>
          <thumbPosXBig>0</thumbPosXBig>
          <thumbPosYBig>0</thumbPosYBig>
          <thumbWidth>165</thumbWidth>
          <thumbHeight>165</thumbHeight>
          <thumbPosX>1</thumbPosX>
          <thumbPosY>1</thumbPosY>
          <thumbZoom>no</thumbZoom>
          <enableFocusZoom>no</enableFocusZoom>
          <zoomXPixels>40</zoomXPixels>
          <zoomYPixels>40</zoomYPixels>
          <hideUnfocusTexture>yes</hideUnfocusTexture>
          <renderFocusText>no</renderFocusText>
          <renderUnfocusText>yes</renderUnfocusText>
          <showFrame>true</showFrame>
          <imageFolder>-</imageFolder>
          <imageFolderFocus>-</imageFolderFocus>
          <textureMask>Picturethumbmask.png</textureMask>
          <frameNoFocus>Picturethumbframe.png</frameNoFocus>
          <frameFocus>Picturethumbframe.png</frameFocus>
          <keepaspectratio>no</keepaspectratio>
          <font>font10</font>
          <spinCanFocus>no</spinCanFocus>
          <dimColor>80ffffff</dimColor>
        </control>
        <control>
          <description>Filmstrip view</description>
          <type>filmstrip</type>
          <colordiffuse>90ffffff</colordiffuse>
          <dimColor>90ffffff</dimColor>
          <posX>7</posX>
          <posY>825</posY>
          <onup>2</onup>
          <ondown>2</ondown>
          <scrollOffset>2</scrollOffset>
          <width>1905</width>
          <height>864</height>
          <thumbWidth>225</thumbWidth>
          <thumbHeight>225</thumbHeight>
          <thumbPosX>0</thumbPosX>
          <thumbPosY>0</thumbPosY>
          <itemWidth>210</itemWidth>
          <itemHeight>240</itemHeight>
          <textureWidth>225</textureWidth>
          <textureHeight>225</textureHeight>
          <frame>Picturethumbframe.png</frame>
          <frameFocus>Picturethumbframe.png</frameFocus>
          <textureMask>Picturethumbmask.png</textureMask>
          <thumbs mask="Picturethumbmask.png">
          </thumbs>
          <background>emtpy.png</background>
          <InfoImage>
          </InfoImage>
          <showFrame>yes</showFrame>
          <showFolder>no</showFolder>
          <showBackGround>no</showBackGround>
          <showInfoImage>no</showInfoImage>
          <keepaspectratio>no</keepaspectratio>
          <dimColor>80ffffff</dimColor>
          <textureUp>arrow_round_right_nofocus.png</textureUp>
          <textureDown>arrow_round_left_nofocus.png</textureDown>
          <textureUpFocus>arrow_round_right_focus.png</textureUpFocus>
          <textureDownFocus>arrow_round_left_focus.png</textureDownFocus>
          <thumbAnimation effect="zoom" start="100,100" end="120,120" time="200" tween="circle" ease="inout">focus</thumbAnimation>
          <thumbAnimation effect="zoom" start="120,120" end="100,100" time="200" tween="back" ease="inout">unfocus</thumbAnimation>
        </control>
        <control>
          <description>Cover Flow view</description>
          <type>coverflow</type>
          <colordiffuse>90ffffff</colordiffuse>
          <dimColor>90ffffff</dimColor>
          <id>50</id>
          <posX>0</posX>
          <posY>300</posY>
          <width>1920</width>
          <height>1080</height>
          <onup>2</onup>
          <onleft>2</onleft>
          <selectedCard>0</selectedCard>
          <cardWidth>540</cardWidth>
          <cardHeight>540</cardHeight>
          <angle>65</angle>
          <sideShift>380</sideShift>
          <sideGap>90</sideGap>
          <sideDepth>550</sideDepth>
          <offsetY>0</offsetY>
          <selectedOffsetY>0</selectedOffsetY>
          <speed>8</speed>
          <backgroundHeight>375</backgroundHeight>
          <backgroundWidth>1920</backgroundWidth>
          <backgroundX>0</backgroundX>
          <backgroundY>705</backgroundY>
          <backgroundDiffuse>FF000000</backgroundDiffuse>
          <background>background2.png</background>
          <showBackground>yes</showBackground>
          <foregroundHeight>720</foregroundHeight>
          <foregroundWidth>1280</foregroundWidth>
          <foregroundX>0</foregroundX>
          <foregroundY>0</foregroundY>
          <foregroundDiffuse>FF000000</foregroundDiffuse>
          <foreground>coverflow_foreground.png</foreground>
          <showForeground>no</showForeground>
          <showFrame>yes</showFrame>
          <frame>Picture_cover2.png</frame>
          <frameFocus>Picture_cover2.png</frameFocus>
          <frameWidth>540</frameWidth>
          <frameHeight>540</frameHeight>
          <spinSpeed>8</spinSpeed>
          <unfocusedAlpha>FF</unfocusedAlpha>
          <folderPrefix>[</folderPrefix>
          <folderSuffix>]</folderSuffix>
          <font1>font13</font1>
          <font2>font10</font2>
          <label1>#selecteditem</label1>
          <label2>#selecteditem2</label2>
          <textcolor>ffffd700</textcolor>
          <remoteColor>FFFF0000</remoteColor>
          <playedColor>FFA0D0FF</playedColor>
          <downloadColor>FF00FF00</downloadColor>
          <selectedColor>FFFFFFFF</selectedColor>
          <shadowAngle>45</shadowAngle>
          <shadowDistance>0</shadowDistance>
          <shadowColor>FF000000</shadowColor>
          <label1YOff>405</label1YOff>
          <label2YOff>430</label2YOff>
          <pageSize>5</pageSize>
          <keepaspectratio>no</keepaspectratio>
          <scrollbarBackground>bar_hor.png</scrollbarBackground>
          <scrollbarLeft>mouse_left_horizontal.png</scrollbarLeft>
          <scrollbarRight>mouse_right_horizontal.png</scrollbarRight>
          <scrollbarYOff>682</scrollbarYOff>
          <showScrollbar>yes</showScrollbar>
          <cards flipY="yes" diffuse="Thumb_Mask.png" mask="Picturethumbmask.png">Picturethumbmask.png</cards>
          <subitems>
            <subitem><![CDATA[                 <controls>
              <control>
                <description>background</description>
                <type>image</type>
                <posX>0</posX>
                <posY>0</posY>
                <width>360</width>
                <height>360</height>
                <texture flipY="yes" diffuse="Thumb_Mask.png" mask="Picturethumbmask.png">Picturethumbmask.png</texture>
              </control>
              <control>
                <description>General Info</description>
                <type>fadelabel</type>
                <posX>20</posX>
                <posY>10</posY>
                <width>320</width>
                <label>#(L(171)) #mvCentral.ArtistName</label>
                <font>font10</font>
                <align>left</align>
                <textcolor>gainsboro</textcolor>
              </control>
          		<control>
          			<id>0</id>
          			<description>Track Description</description>
          			<type>textboxscrollup</type>
          			<posX>20</posX>
          			<posY>94</posY>
          			<width>320</width>
          			<height>120</height>
          			<label>#mvCentral.Description</label>
          			<seperator>-----------------------------------------------------------------------------------</seperator>
          			<font>font9</font>
                <lineSpacing>2</lineSpacing>
          			<scrollStartDelaySec>10</scrollStartDelaySec>
         		  </control>
               <control>
                <description>SD/HD Fullscreen/Widescreen</description>
                <type>image</type>
                <posX>20</posX>
                <posY>40</posY>
                <width>65</width>
                <height>44</height>
                <texture>Logos\#mvCentral.LocalMedia.videoresolution.png</texture>
              </control>
              <!-- Video Codecs -->
              <control>
                <description>Video Codecs</description>
                <type>image</type>
                <posX>140</posX>
                <posY>40</posY>
                <width>65</width>
                <height>44</height>
                <texture>Logos\#mvCentral.LocalMedia.videocodec.png</texture>
              </control>
              <!-- Audio Channels / Codecs-->
              <control>
                <description>Audio Codecs / Channels</description>
                <type>image</type>
                <posX>250</posX>
                <posY>40</posY>
                <width>65</width>
                <height>44</height>
                <texture>Logos\#mvCentral.LocalMedia.audiochannels.png</texture>
              </control>
            </controls>]]></subitem>
          </subitems>
        </control>
      </control>
    </control>
  </controls>
</window>
<!--Checksum:a03673c552ac0c99bac6e4c1b390d6b6-->
