<?xml version="1.0" encoding="utf-8" standalone="yes"?>
<window>
  <id>2011</id>
  <defaultcontrol>5</defaultcontrol>
  <allowoverlay>no</allowoverlay>
  <controls>
	
  <control>
		<description>overlay</description>
		<type>image</type>
		<id>0</id>
		<width>1920</width>
		<height>1080</height>
		<texture>music_info_overlay.png</texture>
		<animation effect="fade" time="450">windowopen</animation>
		<animation effect="fade" time="400">windowclose</animation>
	</control>
	
	<control>
		<description>background</description>
		<type>image</type>
		<id>1</id>
		<posX>165</posX>
		<posY>81</posY>
		<width>1590</width>
		<height>811</height>
		<texture>music_info_bg.png</texture>
		<animation effect="fade" time="250">WindowOpen</animation>
		<animation effect="fade" time="0">WindowClose</animation>
		<animation effect="slide" start="0,250" end="0,0" tween="quadratic" easing="in" time="200" delay="0">WindowOpen</animation>
	</control>
	
  <control>
    <description>Album art</description>
    <type>image</type>
    <id>1</id>
    <posX>281</posX>
    <posY>196</posY>
    <width>427</width>
    <height>427</height>
    <texture>music_info_poster_shadow.png</texture>
    <visible>Control.HasThumb(500)</visible>
		<animation effect="fade" time="250">WindowOpen</animation>
		<animation effect="fade" time="0">WindowClose</animation>
		<animation effect="slide" start="0,250" end="0,0" tween="quadratic" easing="in" time="200" delay="0">WindowOpen</animation>
  </control>
  
  <control>
    <description>Album art</description>
    <type>image</type>
    <id>500</id>
    <posX>287</posX>
    <posY>201</posY>
    <width>409</width>
    <height>409</height>
    <texture>#ArtistInfo.Thumb</texture>
		<animation effect="fade" time="250">WindowOpen</animation>
		<animation effect="fade" time="0">WindowClose</animation>
		<animation effect="slide" start="0,250" end="0,0" tween="quadratic" easing="in" time="200" delay="0">WindowOpen</animation>
  </control>
  
  <control>
    <description>Artist value</description>
    <type>label</type>
    <id>0</id>
		<posX>750</posX>
		<posY>194</posY>
		<textcolor>FF393939</textcolor>
		<font>font22</font>
    <label>#ArtistInfo.Artist</label>
		<animation effect="fade" time="250">WindowOpen</animation>
		<animation effect="fade" time="0">WindowClose</animation>
		<animation effect="slide" start="0,250" end="0,0" tween="quadratic" easing="in" time="200" delay="0">WindowOpen</animation>
  </control>
  
  <control>
    <description>Born</description>
    <type>label</type>
    <id>0</id>
		<posX>750</posX>
		<posY>280</posY>
		<textcolor>FF393939</textcolor>
		<font>TitanLight12</font>
		<label>#(string.rtrim(L(686),' :'))</label>
		<animation effect="fade" time="250">WindowOpen</animation>
		<animation effect="fade" time="0">WindowClose</animation>
		<animation effect="slide" start="0,250" end="0,0" tween="quadratic" easing="in" time="200" delay="0">WindowOpen</animation>
  </control>
  
  <control>
    <description>Years Active</description>
    <type>label</type>
    <id>0</id>
		<posX>750</posX>
		<posY>318</posY>
		<label>#(string.rtrim(L(687),' :'))</label>
		<textcolor>FF393939</textcolor>
		<font>TitanLight12</font>
		<animation effect="fade" time="250">WindowOpen</animation>
		<animation effect="fade" time="0">WindowClose</animation>
		<animation effect="slide" start="0,250" end="0,0" tween="quadratic" easing="in" time="200" delay="0">WindowOpen</animation>
  </control>
  
  <control>
    <description>Genres</description>
    <type>label</type>
    <id>0</id>
		<posX>750</posX>
		<posY>354</posY>
		<label>135</label>
		<textcolor>FF393939</textcolor>
		<font>TitanLight12</font>
		<animation effect="fade" time="250">WindowOpen</animation>
		<animation effect="fade" time="0">WindowClose</animation>
		<animation effect="slide" start="0,250" end="0,0" tween="quadratic" easing="in" time="200" delay="0">WindowOpen</animation>
  </control>
  
  <control>
    <description>Tones</description>
    <type>label</type>
    <id>0</id>
		<posX>750</posX>
		<posY>390</posY>
		<label>#(string.rtrim(L(175),' :'))</label>
		<textcolor>FF393939</textcolor>
		<font>TitanLight12</font>
		<animation effect="fade" time="250">WindowOpen</animation>
		<animation effect="fade" time="0">WindowClose</animation>
		<animation effect="slide" start="0,250" end="0,0" tween="quadratic" easing="in" time="200" delay="0">WindowOpen</animation>
  </control>
  
  <control>
    <description>Styles</description>
    <type>label</type>
    <id>0</id>
		<posX>750</posX>
		<posY>426</posY>
		<label>#(string.rtrim(L(176),' :'))</label>
		<textcolor>FF393939</textcolor>
		<font>TitanLight12</font>
		<animation effect="fade" time="250">WindowOpen</animation>
		<animation effect="fade" time="0">WindowClose</animation>
		<animation effect="slide" start="0,250" end="0,0" tween="quadratic" easing="in" time="200" delay="0">WindowOpen</animation>
  </control>
  
  <control>
    <description>Born value</description>
    <type>label</type>
    <id>0</id>
    <posX>951</posX>
    <posY>280</posY>
    <width>800</width>
  	<label>#ArtistInfo.Born</label>
  	<textcolor>FF393939</textcolor>
		<font>TitanLight12</font>
		<animation effect="fade" time="250">WindowOpen</animation>
		<animation effect="fade" time="0">WindowClose</animation>
		<animation effect="slide" start="0,250" end="0,0" tween="quadratic" easing="in" time="200" delay="0">WindowOpen</animation>
  </control>
  
  <control>
    <description>Years Active value</description>
    <type>label</type>
    <id>0</id>
		<posX>951</posX>
		<posY>318</posY>
		<width>560</width>
		<label>#ArtistInfo.YearsActive</label>
		<textcolor>FF393939</textcolor>
		<font>TitanLight12</font>
		<animation effect="fade" time="250">WindowOpen</animation>
		<animation effect="fade" time="0">WindowClose</animation>
		<animation effect="slide" start="0,250" end="0,0" tween="quadratic" easing="in" time="200" delay="0">WindowOpen</animation>
  </control>
  
  <control>
    <description>Genres value</description>
    <type>label</type>
    <id>0</id>
		<posX>951</posX>
		<posY>354</posY>
		<label>#ArtistInfo.Genres</label>
		<textcolor>FF393939</textcolor>
		<font>TitanLight12</font>
		<animation effect="fade" time="250">WindowOpen</animation>
		<animation effect="fade" time="0">WindowClose</animation>
		<animation effect="slide" start="0,250" end="0,0" tween="quadratic" easing="in" time="200" delay="0">WindowOpen</animation>
  </control>
 
  <control>
    <description>Tones value</description>
    <type>fadelabel</type>
    <id>0</id>
		<posX>951</posX>
		<posY>390</posY>
		<width>680</width>
		<label>#ArtistInfo.Tones</label>
		<textcolor>FF393939</textcolor>
		<font>TitanLight12</font>
		<animation effect="fade" time="250">WindowOpen</animation>
		<animation effect="fade" time="0">WindowClose</animation>
		<animation effect="slide" start="0,250" end="0,0" tween="quadratic" easing="in" time="200" delay="0">WindowOpen</animation>
  </control>
  
  <control>
    <description>Styles value</description>
    <type>fadelabel</type>
    <id>0</id>
		<posX>951</posX>
		<posY>426</posY>
    <width>680</width>
		<label>#ArtistInfo.Styles</label>
		<textcolor>FF393939</textcolor>
		<font>TitanLight12</font>
		<animation effect="fade" time="250">WindowOpen</animation>
		<animation effect="fade" time="0">WindowClose</animation>
		<animation effect="slide" start="0,250" end="0,0" tween="quadratic" easing="in" time="200" delay="0">WindowOpen</animation>
  </control>
  
	<control>
		<description>textarea</description>
		<type>textboxscrollup</type>
		<id>0</id>
		<posX>750</posX>
		<posY>468</posY>
		<width>860</width>
		<height>300</height>
		<textcolor>FF393939</textcolor>
    <font>TitanLight12</font>
		<animation effect="fade" time="250">WindowOpen</animation>
		<animation effect="fade" time="0">WindowClose</animation>
		<animation effect="slide" start="0,250" end="0,0" tween="quadratic" easing="in" time="200" delay="0">WindowOpen</animation>
		<label>#ArtistInfo.Bio</label>
		<visible>!skin.hassetting(#ArtistInfo.ShowAlbums)</visible>
	</control>
	<control>
		<description>textarea</description>
		<type>textboxscrollup</type>
		<id>0</id>
		<posX>750</posX>
		<posY>468</posY>
		<width>860</width>
		<height>300</height>
		<textcolor>FF393939</textcolor>
    <font>TitanLight12</font>
		<animation effect="fade" time="250">WindowOpen</animation>
		<animation effect="fade" time="0">WindowClose</animation>
		<animation effect="slide" start="0,250" end="0,0" tween="quadratic" easing="in" time="200" delay="0">WindowOpen</animation>	
		<label>#ArtistInfo.Albums</label>
		<visible>skin.hassetting(#ArtistInfo.ShowAlbums)</visible>
	</control>
	
	<control>
		<description>Bio/Albums</description>
		<type>button</type>
		<id>5</id>
		<posX>437</posX>
		<posY>653</posY>
    <width>261</width>
    <height>58</height>
		<onleft>5</onleft>
		<onright>4</onright>
		<onup>6</onup>
		<ondown>6</ondown>
		<textcolor>FF000000</textcolor>
		<textcolorNoFocus>FF393939</textcolorNoFocus>
		<textureFocus>button_music_info_focus.png</textureFocus>
		<textureNoFocus>button_music_info_nofocus.png</textureNoFocus>
		<animation effect="fade" time="250">WindowOpen</animation>
		<animation effect="fade" time="0">WindowClose</animation>
		<animation effect="slide" start="0,250" end="0,0" tween="quadratic" easing="in" time="200" delay="0">WindowOpen</animation>
		<onclick>#(skin.togglesetting('#ArtistInfo.ShowAlbums'))</onclick>
		<label>#(L(689)) / #(L(132))</label>
	</control>
  
	<control>
		<description>Refresh</description>
		<type>button</type>
		<id>6</id>
		<posX>437</posX>
		<posY>720</posY>
    <width>261</width>
    <height>58</height>
		<label>184</label>
		<onleft>6</onleft>
		<onright>4</onright>
		<onup>5</onup>
		<ondown>5</ondown>
		<textcolor>FF000000</textcolor>
		<textcolorNoFocus>FF393939</textcolorNoFocus>
		<textureFocus>button_music_info_focus.png</textureFocus>
		<textureNoFocus>button_music_info_nofocus.png</textureNoFocus>
		<animation effect="fade" time="250">WindowOpen</animation>
		<animation effect="fade" time="0">WindowClose</animation>
		<animation effect="slide" start="0,250" end="0,0" tween="quadratic" easing="in" time="200" delay="0">WindowOpen</animation>
	</control>
  </controls>
</window>
