<?xml version="1.0" encoding="utf-8" standalone="yes"?>
<window>
  <controls>
	

	  <control>
		<description>button group</description>
		<type>group</type>
		<posX>60</posX>
		<posY>420</posY>
		<!-- Remove and Gaps when buttons are not visible -->
		<layout>StackLayout(0, Horizontal, false)</layout>
		<visible allowhiddenfocus="true">control.hasfocus(250)|control.hasfocus(251)|control.hasfocus(252)|control.hasfocus(253)|control.hasfocus(254)|control.hasfocus(255)|control.hasfocus(256)|control.hasfocus(257)|control.hasfocus(258)|control.hasfocus(259)|control.hasfocus(350)|control.hasfocus(351)|control.hasfocus(352)|control.hasfocus(353)|control.hasfocus(354)|control.hasfocus(411)|control.hasfocus(412)|control.hasfocus(413)|control.hasfocus(414)|control.hasfocus(415)</visible>   
	  <control>
        <description>Page1 Button1</description>
        <type>menubutton</type>
        <id>250</id>
        <width>69</width>
        <height>66</height>
		<textXOff>5</textXOff>
        <textYOff>3</textYOff>
		<oninfo>#(skin.setfocus(35,00510))</oninfo>
        <mode>dialoglist</mode>
        <dialogTitle>Choose a plugin</dialogTitle>
        <valueTextInButton>no</valueTextInButton>
        <valuePrefixText> Plugin : </valuePrefixText>
        <onclick>#(skin.setstring('#tile11plugin.hyperlink',#selectedlabel250))</onclick>
        <binding>#tile11plugin.hyperlink</binding>
        <subitems>
        <subitem>#pluginlist</subitem>
        </subitems>
        <textcolorNoFocus>70ffffff</textcolorNoFocus>
        <textureFocus>pluge.png</textureFocus>
		<textureNoFocus>plugd.png</textureNoFocus>
		<onup>250</onup>
        <onleft>250</onleft>
        <ondown>411</ondown>
        <onright>350</onright>
      </control>
	  <control>
        <description>Page3 Button1</description>
        <type>menubutton</type>
        <id>350</id>
        <width>69</width>
        <height>66</height>
		<oninfo>#(skin.setfocus(35,00510))</oninfo>
        <label></label>
		<font>font111</font>
		<textcolorNoFocus>99ffffff</textcolorNoFocus>
        <onclick>#(skin.setstring('#tile11plugin.name'))</onclick>
        <textureFocus>lblfocus.png</textureFocus>
		<textureNoFocus>lblnofocus.png</textureNoFocus>
		<onup>350</onup>
        <onleft>250</onleft>
        <ondown>00510</ondown>
        <onright>251</onright>
      </control>	  
	  
	  <control>
        <description>DUMMY</description>
        <type>button</type>
        <id>0</id>
        <width>10</width>
		<height>32</height>
        <label></label>
		<font>font111</font>
		<textcolorNoFocus>99ffffff</textcolorNoFocus>
		<textureFocus></textureFocus>
		<textureNoFocus></textureNoFocus>
      </control>	  
	  
	  <!--MAIN MOVIES HYPERLINK PARAMETER-->.
	  <control>
        <description>Page1 Button1</description>
        <type>button</type>
        <id>251</id>
        <width>69</width>
        <height>66</height>
		<oninfo>#(skin.setfocus(35,00510))</oninfo>
        <label></label>
		<font>font111</font>
		<textcolorNoFocus>99ffffff</textcolorNoFocus>
		<textureFocus>menu.png</textureFocus>
		<textureNoFocus></textureNoFocus>
        <onclick>#(skin.setstring('#tile11plugin.parameter'))</onclick>
		<onup>251</onup>
        <onleft>350</onleft>
        <ondown>00510</ondown>
        <onright>252</onright>		
      </control>
	  <!--HYPERLINK PARAMETER-->		 

	  <control>
        <description>DUMMY</description>
        <type>button</type>
        <id>0</id>
        <width>150</width>
		<height>32</height>
        <label></label>
		<font>font111</font>
		<textcolorNoFocus>99ffffff</textcolorNoFocus>
		<textureFocus></textureFocus>
		<textureNoFocus></textureNoFocus>
      </control>
	  
	  
	  <!--##############################################################################################-->
	  <!--##############################################################################################-->
	  
	  <control>
        <description>Page1 Button2</description>
        <type>menubutton</type>
        <id>252</id>
        <width>69</width>
        <height>66</height>
		<textXOff>5</textXOff>
        <textYOff>3</textYOff>
		<oninfo>#(skin.setfocus(35,00511))</oninfo>
        <mode>dialoglist</mode>
        <dialogTitle>Choose a plugin</dialogTitle>
        <valueTextInButton>no</valueTextInButton>
        <valuePrefixText> Plugin : </valuePrefixText>
        <onclick>#(skin.setstring('#tile12plugin.hyperlink',#selectedlabel252))</onclick>
        <binding>#tile12plugin.hyperlink</binding>
        <subitems>
        <subitem>#pluginlist</subitem>
        </subitems>
        <textcolorNoFocus>70ffffff</textcolorNoFocus>
        <textureFocus>pluge.png</textureFocus>
		<textureNoFocus>plugd.png</textureNoFocus>
		<onup>252</onup>
        <onleft>251</onleft>
        <ondown>412</ondown>
        <onright>351</onright>
      </control>
	  
	  <control>
        <description>Page3 Button1</description>
        <type>menubutton</type>
        <id>351</id>
        <width>69</width>
        <height>66</height>
		<oninfo>#(skin.setfocus(35,00511))</oninfo>
        <label></label>
		<font>font111</font>
		<textcolorNoFocus>99ffffff</textcolorNoFocus>
        <onclick>#(skin.setstring('#tile12plugin.name'))</onclick>
        <textureFocus>lblfocus.png</textureFocus>
		<textureNoFocus>lblnofocus.png</textureNoFocus>
		<onup>351</onup>
        <onleft>252</onleft>
        <ondown>00511</ondown>
        <onright>253</onright>
      </control>		  
	  
	  <control>
        <description>DUMMY</description>
        <type>button</type>
        <id>0</id>
        <width>10</width>
		<height>32</height>
        <label></label>
		<font>font111</font>
		<textcolorNoFocus>99ffffff</textcolorNoFocus>
		<textureFocus></textureFocus>
		<textureNoFocus></textureNoFocus>
      </control>		  
	  
	  <!--MAIN MOVIES HYPERLINK PARAMETER-->.
	  <control>
        <description>Page1 Button2</description>
        <type>button</type>
        <id>253</id>
        <width>69</width>
        <height>66</height>
		<oninfo>#(skin.setfocus(35,00511))</oninfo>
        <label></label>
		<font>font111</font>
		<textcolorNoFocus>99ffffff</textcolorNoFocus>
		<textureFocus>menu.png</textureFocus>
		<textureNoFocus></textureNoFocus>
        <onclick>#(skin.setstring('#tile12plugin.parameter'))</onclick>
		<onup>253</onup>
        <onleft>351</onleft>
        <ondown>00511</ondown>
        <onright>254</onright>
      </control>
	  <!--HYPERLINK PARAMETER-->
	  
	  <control>
        <description>DUMMY</description>
        <type>button</type>
        <id>0</id>
        <width>153</width>
		<height>32</height>
        <label></label>
		<font>font111</font>
		<textcolorNoFocus>99ffffff</textcolorNoFocus>
		<textureFocus></textureFocus>
		<textureNoFocus></textureNoFocus>
      </control>
	  
	  
	  <!--##############################################################################################-->
	  <!--##############################################################################################-->
	  
	  <control>
        <description>Page1 Button2</description>
        <type>menubutton</type>
        <id>254</id>
        <width>69</width>
        <height>66</height>
		<textXOff>5</textXOff>
        <textYOff>3</textYOff>
		<oninfo>#(skin.setfocus(35,00512))</oninfo>
        <mode>dialoglist</mode>
        <dialogTitle>Choose a plugin</dialogTitle>
        <valueTextInButton>no</valueTextInButton>
        <valuePrefixText> Plugin : </valuePrefixText>
        <onclick>#(skin.setstring('#tile13plugin.hyperlink',#selectedlabel254))</onclick>
        <binding>#tile13plugin.hyperlink</binding>
        <subitems>
        <subitem>#pluginlist</subitem>
        </subitems>
        <textcolorNoFocus>70ffffff</textcolorNoFocus>
        <textureFocus>pluge.png</textureFocus>
		<textureNoFocus>plugd.png</textureNoFocus>
		<onup>254</onup>
        <onleft>253</onleft>
        <ondown>413</ondown>
        <onright>352</onright>
      </control>
	  <control>
        <description>Page3 Button1</description>
        <type>menubutton</type>
        <id>352</id>
        <width>69</width>
        <height>66</height>
		<oninfo>#(skin.setfocus(35,00512))</oninfo>
        <label></label>
		<font>font111</font>
		<textcolorNoFocus>99ffffff</textcolorNoFocus>
        <onclick>#(skin.setstring('#tile13plugin.name'))</onclick>
        <textureFocus>lblfocus.png</textureFocus>
		<textureNoFocus>lblnofocus.png</textureNoFocus>
		<onup>352</onup>
        <onleft>254</onleft>
        <ondown>00512</ondown>
        <onright>255</onright>
      </control>
	  
	  <control>
        <description>DUMMY</description>
        <type>button</type>
        <id>0</id>
        <width>10</width>
		<height>32</height>
        <label></label>
		<font>font111</font>
		<textcolorNoFocus>99ffffff</textcolorNoFocus>
		<textureFocus></textureFocus>
		<textureNoFocus></textureNoFocus>
      </control>		  
	  
	  <!--MAIN MOVIES HYPERLINK PARAMETER-->.
	  <control>
        <description>Page1 Button2</description>
        <type>button</type>
        <id>255</id>
        <width>69</width>
        <height>66</height>
		<oninfo>#(skin.setfocus(35,00512))</oninfo>
        <label></label>
		<font>font111</font>
		<textcolorNoFocus>99ffffff</textcolorNoFocus>
		<textureFocus>menu.png</textureFocus>
		<textureNoFocus></textureNoFocus>
        <onclick>#(skin.setstring('#tile13plugin.parameter'))</onclick>
		<onup>255</onup>
        <onleft>352</onleft>
        <ondown>00512</ondown>
        <onright>256</onright>
      </control>
	  <!--HYPERLINK PARAMETER-->
	  
	  <control>
        <description>DUMMY</description>
        <type>button</type>
        <id>0</id>
        <width>153</width>
		<height>32</height>
        <label></label>
		<font>font111</font>
		<textcolorNoFocus>99ffffff</textcolorNoFocus>
		<textureFocus></textureFocus>
		<textureNoFocus></textureNoFocus>
      </control>	  

	  
	  <!--##############################################################################################-->
	  <!--##############################################################################################-->
	  
	  <control>
        <description>Page1 Button2</description>
        <type>menubutton</type>
        <id>256</id>
        <width>69</width>
        <height>66</height>
		<textXOff>5</textXOff>
        <textYOff>3</textYOff>
		<oninfo>#(skin.setfocus(35,00513))</oninfo>
        <mode>dialoglist</mode>
        <dialogTitle>Choose a plugin</dialogTitle>
        <valueTextInButton>no</valueTextInButton>
        <valuePrefixText> Plugin : </valuePrefixText>
        <onclick>#(skin.setstring('#tile14plugin.hyperlink',#selectedlabel256))</onclick>
        <binding>#tile14plugin.hyperlink</binding>
        <subitems>
        <subitem>#pluginlist</subitem>
        </subitems>
        <textcolorNoFocus>70ffffff</textcolorNoFocus>
        <textureFocus>pluge.png</textureFocus>
		<textureNoFocus>plugd.png</textureNoFocus>
		<onup>256</onup>
        <onleft>255</onleft>
        <ondown>414</ondown>
        <onright>353</onright>
      </control>
	  
	  <control>
        <description>Page3 Button1</description>
        <type>menubutton</type>
        <id>353</id>
        <width>69</width>
        <height>66</height>
		<oninfo>#(skin.setfocus(35,00513))</oninfo>
        <label></label>
		<font>font111</font>
		<textcolorNoFocus>99ffffff</textcolorNoFocus>
        <onclick>#(skin.setstring('#tile14plugin.name'))</onclick>
        <textureFocus>lblfocus.png</textureFocus>
		<textureNoFocus>lblnofocus.png</textureNoFocus>
		<onup>352</onup>
        <onleft>256</onleft>
        <ondown>00513</ondown>
        <onright>257</onright>
      </control>	  
	  
	  <control>
        <description>DUMMY</description>
        <type>button</type>
        <id>0</id>
        <width>10</width>
		<height>32</height>
        <label></label>
		<font>font111</font>
		<textcolorNoFocus>99ffffff</textcolorNoFocus>
		<textureFocus></textureFocus>
		<textureNoFocus></textureNoFocus>
      </control>		  
	  
	  <!--MAIN MOVIES HYPERLINK PARAMETER-->.
	  <control>
        <description>Page1 Button2</description>
        <type>button</type>
        <id>257</id>
        <width>69</width>
        <height>66</height>
		<oninfo>#(skin.setfocus(35,00513))</oninfo>
        <label></label>
		<font>font111</font>
		<textcolorNoFocus>99ffffff</textcolorNoFocus>
		<textureFocus>menu.png</textureFocus>
		<textureNoFocus></textureNoFocus>
        <onclick>#(skin.setstring('#tile14plugin.parameter'))</onclick>
		<onup>257</onup>
        <onleft>353</onleft>
        <ondown>00513</ondown>
        <onright>258</onright>
      </control>
	  <!--HYPERLINK PARAMETER-->
	  
	  <control>
        <description>DUMMY</description>
        <type>button</type>
        <id>0</id>
        <width>153</width>
		<height>32</height>
        <label></label>
		<font>font111</font>
		<textcolorNoFocus>99ffffff</textcolorNoFocus>
		<textureFocus></textureFocus>
		<textureNoFocus></textureNoFocus>
      </control>	  
	  
	  

	  <!--##############################################################################################-->
	  <!--##############################################################################################-->
	  
	  <control>
        <description>Page1 Button2</description>
        <type>menubutton</type>
        <id>258</id>
        <width>69</width>
        <height>66</height>
		<textXOff>5</textXOff>
        <textYOff>3</textYOff>
		<oninfo>#(skin.setfocus(35,00514))</oninfo>
        <mode>dialoglist</mode>
        <dialogTitle>Choose a plugin</dialogTitle>
        <valueTextInButton>no</valueTextInButton>
        <valuePrefixText> Plugin : </valuePrefixText>
        <onclick>#(skin.setstring('#tile15plugin.hyperlink',#selectedlabel258))</onclick>
        <binding>#tile15plugin.hyperlink</binding>
        <subitems>
        <subitem>#pluginlist</subitem>
        </subitems>
        <textcolorNoFocus>70ffffff</textcolorNoFocus>
        <textureFocus>pluge.png</textureFocus>
		<textureNoFocus>plugd.png</textureNoFocus>
		<onup>258</onup>
        <onleft>257</onleft>
        <ondown>415</ondown>
        <onright>354</onright>
      </control>
	  
	  <control>
        <description>Page3 Button1</description>
        <type>menubutton</type>
        <id>354</id>
        <width>69</width>
        <height>66</height>
		<oninfo>#(skin.setfocus(35,00514))</oninfo>
        <label></label>
		<font>font111</font>
		<textcolorNoFocus>99ffffff</textcolorNoFocus>
        <onclick>#(skin.setstring('#tile15plugin.name'))</onclick>
        <textureFocus>lblfocus.png</textureFocus>
		<textureNoFocus>lblnofocus.png</textureNoFocus>
		<onup>352</onup>
        <onleft>258</onleft>
        <ondown>00514</ondown>
        <onright>259</onright>
      </control>	  
	  
	  <control>
        <description>DUMMY</description>
        <type>button</type>
        <id>0</id>
        <width>10</width>
		<height>32</height>
        <label></label>
		<font>font111</font>
		<textcolorNoFocus>99ffffff</textcolorNoFocus>
		<textureFocus></textureFocus>
		<textureNoFocus></textureNoFocus>
      </control>		  
	  
	  <!--MAIN MOVIES HYPERLINK PARAMETER-->.
	  <control>
        <description>Page1 Button2</description>
        <type>button</type>
        <id>259</id>
        <width>69</width>
        <height>66</height>
		<oninfo>#(skin.setfocus(35,00514))</oninfo>
        <label></label>
		<font>font111</font>
		<textcolorNoFocus>99ffffff</textcolorNoFocus>
		<textureFocus>menu.png</textureFocus>
		<textureNoFocus></textureNoFocus>
        <onclick>#(skin.setstring('#tile15plugin.parameter'))</onclick>
		<onup>259</onup>
        <onleft>354</onleft>
        <ondown>00514</ondown>
        <onright>250</onright>
      </control>
	  <!--HYPERLINK PARAMETER-->
	  




	  
	  
	  
	  
      </control>

  </controls>
</window>